f_comparator.v
`timescale 1ns/10ps
module f_comparator (
    input [31:0] in0,
    input [31:0] in1,
    output res
);

wire [30:0] abs_in0, abs_in1;

assign abs_in0 = in0[30:0];
assign abs_in1 = in1[30:0];
assign res = abs_in0 > abs_in1; 

endmodule

f_adder/f_adder.v
`timescale 1ns/10ps
`include "../f_comparator.v"
module f_adder (
    input clk,
    input rstn,
    input [31:0] in0,
    input [31:0] in1,
    input op,
    output reg [31:0] out

);

wire in0_bt_in1;
reg [31:0] bigger;
reg [31:0] smaller;
reg check_sign;
reg [7:0] exp;
reg [31:0] result;

f_comparator u_f_comparator(
    .in0(in0),
    .in1(in1),
    .res(in0_bt_in1)
);

always@(posedge clk, negedge rstn)begin
    if(!rstn) begin
        bigger <= {32{1'b0}};
        smaller <= {32{1'b0}};
        exp <= {8{1'b0}};
        result <= {32{1'b0}};
        check_sign <= 1'b0;
    end else begin
        //1 cycle delay...
        out <= result;
    end
end

always@(*)begin
    //check sign..
    if(!op) 
        check_sign = in1[31];
    else 
        check_sign = ~in1[31];

    //set bigger..
    bigger = (in0_bt_in1 == 1) ? in0 : {check_sign,in1[30:0]};
    smaller = (in0_bt_in1 == 0) ? in0 : {check_sign,in1[30:0]};

    //cal exp 
    exp = bigger[30:23] - smaller[30:23];

    //shift 
    smaller[22:0] = smaller[22:0] >> exp;

    // //cal  
    smaller[23:0] = (op == 0) ? (bigger[22:0] + smaller[22:0]) : (bigger[22:0] - smaller[22:0]);

    //carry 
    if(smaller[23]==1'b1 && bigger[30:23] != 8'hff)
        bigger[30:23] = bigger[30:23] + {{7{1'b0}},1'b1};
    //we use bigger sign 
    bigger[22:0] = smaller[22:0];
    //save result 
    result = bigger;
end
    
endmodule

f_adder/f_adder_tb.v
`timescale 1ns/10ps
`include "f_adder.v"
module f_adder_tb;
    reg clk,rstn;
    reg [31:0] in0, in1;
    reg op;
    wire [31:0] out;

//call dut
f_adder u_f_adder(
    .clk(clk),
    .rstn(rstn),
    .in0(in0),
    .in1(in1),
    .op(op),
    .out(out)
);

//clk gen
always #5 clk = ~clk;

integer i;
integer f;
initial begin
    $dumpfile("f_adder.vcd");
    $dumpvars(1);
end

initial begin
    f = $fopen("f_adder_log.txt");
    $display("init val... [%0d]\n",$time);
    rstn = 0;
    clk = 0;
    op = 0;
    in0 = 0;
    in1 = 0;
    $display("reset...![%0d]\n",$time);
    #100
        rstn = 0;
    #10
        rstn = 1;
    #10
    $display("push random data..[%0d]\n",$time);
    //do.. add..
    for(i=0;i<32;i++)begin
        @(posedge clk);
        in0=$random;
        in1=$random;
        op=0;
        $fwrite(f,"%d\n",op);
        $fwrite(f,"%b\n",in0);
        $fwrite(f,"%b\n",in1);
        #1
        $fwrite(f,"%b\n",out);
    end    
    
    //do.. sub..
    for(i=0;i<32;i++) begin
        @(posedge clk);
        in0=$random;
        in1=$random;
        op=1;
        $fwrite(f,"%d\n",op);
        $fwrite(f,"%b\n",in0);
        $fwrite(f,"%b\n",in1);
        #1
        $fwrite(f,"%b\n",out);
    end
    @(posedge clk);
        in0=0;
        in1=0;
        op=1;
        $fwrite(f,"%d\n",op);
        $fwrite(f,"%b\n",in0);
        $fwrite(f,"%b\n",in1);
        #1
        $fwrite(f,"%b\n",out);
    $display("done!\n");
    #10 $finish;
end

endmodule

f_adder/f_adder.vcd
$date
	Sat Nov 19 15:49:46 2022
$end
$version
	Icarus Verilog
$end
$timescale
	10ps
$end
$scope module f_adder_tb $end
$var wire 32 ! out [31:0] $end
$var reg 1 " clk $end
$var reg 32 # in0 [31:0] $end
$var reg 32 $ in1 [31:0] $end
$var reg 1 % op $end
$var reg 1 & rstn $end
$var integer 32 ' f [31:0] $end
$var integer 32 ( i [31:0] $end
$scope module u_f_adder $end
$var wire 1 " clk $end
$var wire 32 ) in0 [31:0] $end
$var wire 32 * in1 [31:0] $end
$var wire 1 % op $end
$var wire 1 & rstn $end
$var wire 1 + in0_bt_in1 $end
$var reg 32 , bigger [31:0] $end
$var reg 1 - check_sign $end
$var reg 8 . exp [7:0] $end
$var reg 32 / out [31:0] $end
$var reg 32 0 result [31:0] $end
$var reg 32 1 smaller [31:0] $end
$scope module u_f_comparator $end
$var wire 32 2 in0 [31:0] $end
$var wire 32 3 in1 [31:0] $end
$var wire 1 + res $end
$var wire 31 4 abs_in1 [30:0] $end
$var wire 31 5 abs_in0 [30:0] $end
$upscope $end
$upscope $end
$upscope $end
$enddefinitions $end
#0
$dumpvars
b0 5
b0 4
b0 3
b0 2
b0 1
b0 0
bx /
b0 .
0-
b0 ,
0+
b0 *
b0 )
bx (
b10 '
0&
0%
b0 $
b0 #
0"
bx !
$end
#500
1"
#1000
0"
#1500
1"
#2000
0"
#2500
1"
#3000
0"
#3500
1"
#4000
0"
#4500
1"
#5000
0"
#5500
1"
#6000
0"
#6500
1"
#7000
0"
#7500
1"
#8000
0"
#8500
1"
#9000
0"
#9500
1"
#10000
0"
#10500
1"
#11000
0"
1&
#11500
b0 !
b0 /
1"
#12000
0"
b0 (
#12500
b1000000100010010101111010000001 4
0+
b10010000101010011010100100100 5
b11000000100010010101111010000001 0
b1011101 .
b10010000010010101111010000001 1
b11000000100010010101111010000001 ,
1-
b11000000100010010101111010000001 $
b11000000100010010101111010000001 *
b11000000100010010101111010000001 3
b10010000101010011010100100100 #
b10010000101010011010100100100 )
b10010000101010011010100100100 2
1"
#12600
b1 (
#13000
0"
#13500
b11000000100010010101111010000001 !
b11000000100010010101111010000001 /
b110001111100000101011001100011 4
b100100001001101011000001001 5
b10110001111100000101011001100011 0
b1011010 .
b10000100011100000101011001100011 1
b10110001111100000101011001100011 ,
b10110001111100000101011001100011 $
b10110001111100000101011001100011 *
b10110001111100000101011001100011 3
b10000100100001001101011000001001 #
b10000100100001001101011000001001 )
b10000100100001001101011000001001 2
1"
#13600
b10 (
#14000
0"
#14500
b10110001111100000101011001100011 !
b10110001111100000101011001100011 /
b1000110110111111001100110001101 4
b110101110010111101100001101 5
b1000110110111111001100110001101 0
b10000000 .
b110010111111001100110001101 1
b1000110110111111001100110001101 ,
0-
b1000110110111111001100110001101 $
b1000110110111111001100110001101 *
b1000110110111111001100110001101 3
b110101110010111101100001101 #
b110101110010111101100001101 )
b110101110010111101100001101 2
1"
#14600
b11 (
#15000
0"
#15500
b1000110110111111001100110001101 !
b1000110110111111001100110001101 /
1+
b1001001101110101001000010010 4
b110010110000101000010001100101 5
b10110010110000101000010001100101 0
b1010011 .
b10001001010000101000010001100101 1
b10110010110000101000010001100101 ,
1-
b10001001001101110101001000010010 $
b10001001001101110101001000010010 *
b10001001001101110101001000010010 3
b10110010110000101000010001100101 #
b10110010110000101000010001100101 )
b10110010110000101000010001100101 2
1"
#15600
b100 (
#16000
0"
#16500
b10110010110000101000010001100101 !
b10110010110000101000010001100101 /
b110110101111100110100001101 4
0+
b111100111110001100000001 5
b110110101111101010001001011 0
b1100 .
b10101111101010001001011 1
b110110101111101010001001011 ,
0-
b110110101111100110100001101 $
b110110101111100110100001101 *
b110110101111100110100001101 3
b111100111110001100000001 #
b111100111110001100000001 )
b111100111110001100000001 2
1"
#16600
b101 (
#17000
0"
#17500
b110110101111101010001001011 !
b110110101111101010001001011 /
b11110100011011100110100111101 4
1+
b111011001000111111000101110110 5
b111011001000111111000101110110 0
b111001 .
b11110001000111111000101110110 1
b111011001000111111000101110110 ,
b11110100011011100110100111101 $
b11110100011011100110100111101 *
b11110100011011100110100111101 3
b111011001000111111000101110110 #
b111011001000111111000101110110 )
b111011001000111111000101110110 2
1"
#17600
b110 (
#18000
0"
#18500
b111011001000111111000101110110 !
b111011001000111111000101110110 /
b1000110001011011111011110001100 4
b1110110110101000101011111101101 5
b1110110110101000101011111101101 0
b1100001 .
b1000110010101000101011111101101 1
b1110110110101000101011111101101 ,
b1000110001011011111011110001100 $
b1000110001011011111011110001100 *
b1000110001011011111011110001100 3
b1110110110101000101011111101101 #
b1110110110101000101011111101101 )
b1110110110101000101011111101101 2
1"
#18600
b111 (
#19000
0"
#19500
b1110110110101000101011111101101 !
b1110110110101000101011111101101 /
b1100011001101110010010011000110 4
b1111100111111011110100111111001 5
b1111100111111011110100111111001 0
b110011 .
b11100011011111011110100111111001 1
b1111100111111011110100111111001 ,
1-
b11100011001101110010010011000110 $
b11100011001101110010010011000110 *
b11100011001101110010010011000110 3
b1111100111111011110100111111001 #
b1111100111111011110100111111001 )
b1111100111111011110100111111001 2
1"
#19600
b1000 (
#20000
0"
#20500
b1111100111111011110100111111001 !
b1111100111111011110100111111001 /
b1010101000100111101001010101010 4
1+
b1100010111101111000010011000101 5
b11100010111101111000010011000101 0
b11011 .
b11010101011101111000010011000101 1
b11100010111101111000010011000101 ,
b11010101000100111101001010101010 $
b11010101000100111101001010101010 *
b11010101000100111101001010101010 3
b11100010111101111000010011000101 #
b11100010111101111000010011000101 )
b11100010111101111000010011000101 2
1"
#20600
b1001 (
#21000
0"
#21500
b11100010111101111000010011000101 !
b11100010111101111000010011000101 /
b111011110100100111001001110111 4
b1110010101011111111011111100101 5
b1110010101011111111011111100101 0
b1101110 .
b10111011001011111111011111100101 1
b1110010101011111111011111100101 ,
b10111011110100100111001001110111 $
b10111011110100100111001001110111 *
b10111011110100100111001001110111 3
b1110010101011111111011111100101 #
b1110010101011111111011111100101 )
b1110010101011111111011111100101 2
1"
#21600
b1010 (
#22000
0"
#22500
b1110010101011111111011111100101 !
b1110010101011111111011111100101 /
b1000111111011001101101110001111 4
0+
b1001001100101101011000010010 5
b1000111111011001101101110001111 0
b1111101 .
b10001001011011001101101110001111 1
b1000111111011001101101110001111 ,
0-
b1000111111011001101101110001111 $
b1000111111011001101101110001111 *
b1000111111011001101101110001111 3
b10001001001100101101011000010010 #
b10001001001100101101011000010010 )
b10001001001100101101011000010010 2
1"
#22600
b1011 (
#23000
0"
#23500
b1000111111011001101101110001111 !
b1000111111011001101101110001111 /
b1100111011101101001011011001110 4
1+
b1111001001100000110100111110010 5
b1111001001100000110100111110010 0
b100100 .
b11100111001100000110100111110010 1
b1111001001100000110100111110010 ,
1-
b11100111011101101001011011001110 $
b11100111011101101001011011001110 *
b11100111011101101001011011001110 3
b1111001001100000110100111110010 #
b1111001001100000110100111110010 )
b1111001001100000110100111110010 2
1"
#23600
b1100 (
#24000
0"
#24500
b1111001001100000110100111110010 !
b1111001001100000110100111110010 /
b1100010110010100100111011000101 4
b1110100000000000111101011101000 5
b11110100000000000111101011101000 0
b100011 .
b11100010000000000111101011101000 1
b11110100000000000111101011101000 ,
b11100010110010100100111011000101 $
b11100010110010100100111011000101 *
b11100010110010100100111011000101 3
b11110100000000000111101011101000 #
b11110100000000000111101011101000 )
b11110100000000000111101011101000 2
1"
#24600
b1101 (
#25000
0"
#25500
b11110100000000000111101011101000 !
b11110100000000000111101011101000 /
b1011110100011100010100010111101 4
0+
b101110010110000100100101011100 5
b11011110100011100010100010111101 0
b1100001 .
b101110000011100010100010111101 1
b11011110100011100010100010111101 ,
b11011110100011100010100010111101 $
b11011110100011100010100010111101 *
b11011110100011100010100010111101 3
b101110010110000100100101011100 #
b101110010110000100100101011100 )
b101110010110000100100101011100 2
1"
#25600
b1110 (
#26000
0"
#26500
b11011110100011100010100010111101 !
b11011110100011100010100010111101 /
b110010101001110010011001100101 4
b10110101010110101100000101101 5
b10110010101001110010011001100101 0
b111000 .
b10010110001001110010011001100101 1
b10110010101001110010011001100101 ,
b10110010101001110010011001100101 $
b10110010101001110010011001100101 *
b10110010101001110010011001100101 3
b10010110101010110101100000101101 #
b10010110101010110101100000101101 )
b10010110101010110101100000101101 2
1"
#26600
b1111 (
#27000
0"
#27500
b10110010101001110010011001100101 !
b10110010101001110010011001100101 /
1+
b101011100111000011100001010 4
b110001111011110110001001100011 5
b10110001111011110110001001100011 0
b1011001 .
b101011011110110001001100011 1
b10110001111011110110001001100011 ,
0-
b101011100111000011100001010 $
b101011100111000011100001010 *
b101011100111000011100001010 3
b10110001111011110110001001100011 #
b10110001111011110110001001100011 )
b10110001111011110110001001100011 2
1"
#27600
b10000 (
#28000
0"
#28500
b10110001111011110110001001100011 !
b10110001111011110110001001100011 /
b10000011001000010000100100000 4
b1000000001110110010001010000000 5
b11000000001110110010001010000000 0
b1100000 .
b10000001110110010001010000000 1
b11000000001110110010001010000000 ,
b10000011001000010000100100000 $
b10000011001000010000100100000 *
b10000011001000010000100100000 3
b11000000001110110010001010000000 #
b11000000001110110010001010000000 )
b11000000001110110010001010000000 2
1"
#28600
b10001 (
#29000
0"
#29500
b11000000001110110010001010000000 !
b11000000001110110010001010000000 /
b1001110110011001100110010011101 4
b1010101011110000100010110101010 5
b1010101011110000100100000010000 0
b1101 .
b11001110011110000100100000010000 1
b1010101011110000100100000010000 ,
1-
b11001110110011001100110010011101 $
b11001110110011001100110010011101 *
b11001110110011001100110010011101 3
b1010101011110000100010110101010 #
b1010101011110000100010110101010 )
b1010101011110000100010110101010 2
1"
#29600
b10010 (
#30000
0"
#30500
b1010101011110000100100000010000 !
b1010101011110000100100000010000 /
b1001100000111011100000010011 4
1+
b1001011001000000011111010010110 5
b11001011001000000011111010010110 0
b10000011 .
b10001001001000000011111010010110 1
b11001011001000000011111010010110 ,
b10001001100000111011100000010011 $
b10001001100000111011100000010011 *
b10001001100000111011100000010011 3
b11001011001000000011111010010110 #
b11001011001000000011111010010110 )
b11001011001000000011111010010110 2
1"
#30600
b10011 (
#31000
0"
#31500
b11001011001000000011111010010110 !
b11001011001000000011111010010110 /
b101001101001111101011001010011 4
0+
b110101111000011100000001101 5
b10101001101001111101011001010011 0
b1000110 .
b10000110001001111101011001010011 1
b10101001101001111101011001010011 ,
b10101001101001111101011001010011 $
b10101001101001111101011001010011 *
b10101001101001111101011001010011 3
b10000110101111000011100000001101 #
b10000110101111000011100000001101 )
b10000110101111000011100000001101 2
1"
#31600
b10100 (
#32000
0"
#32500
b10101001101001111101011001010011 !
b10101001101001111101011001010011 /
b1101010101001100010101011010101 4
0+
b110101100111111101110101101011 5
b11101010101001100010101011010101 0
b1101010 .
b110101001001100010101011010101 1
b11101010101001100010101011010101 ,
b11101010101001100010101011010101 $
b11101010101001100010101011010101 *
b11101010101001100010101011010101 3
b110101100111111101110101101011 #
b110101100111111101110101101011 )
b110101100111111101110101101011 2
1"
#32600
b10101 (
#33000
0"
#33500
b11101010101001100010101011010101 !
b11101010101001100010101011010101 /
b1010111010101100011111010101110 4
b1000101110100101000000010 5
b11010111010101100011111010101110 0
b10101100 .
b10000001010101100011111010101110 1
b11010111010101100011111010101110 ,
b11010111010101100011111010101110 $
b11010111010101100011111010101110 *
b11010111010101100011111010101110 3
b10000001000101110100101000000010 #
b10000001000101110100101000000010 )
b10000001000101110100101000000010 2
1"
#33600
b10110 (
#34000
0"
#34500
b11010111010101100011111010101110 !
b11010111010101100011111010101110 /
b1100111110001010111001011001111 4
b1110111111111110100100011101 5
b11100111110001010111001011001111 0
b10110010 .
b1110010001010111001011001111 1
b11100111110001010111001011001111 ,
b11100111110001010111001011001111 $
b11100111110001010111001011001111 *
b11100111110001010111001011001111 3
b1110111111111110100100011101 #
b1110111111111110100100011101 )
b1110111111111110100100011101 2
1"
#34600
b10111 (
#35000
0"
#35500
b11100111110001010111001011001111 !
b11100111110001010111001011001111 /
1+
b101000010010110010100001010 4
b10001100001000100100100100011 5
b10001100001000100100100100011 0
b11001 .
b101000001000100100100100011 1
b10001100001000100100100100011 ,
0-
b101000010010110010100001010 $
b101000010010110010100001010 *
b101000010010110010100001010 3
b10001100001000100100100100011 #
b10001100001000100100100100011 )
b10001100001000100100100100011 2
1"
#35600
b11000 (
#36000
0"
#36500
b10001100001000100100100100011 !
b10001100001000100100100100011 /
b11110001100010100110000111100 4
b1100101011100110000101011001010 5
b11100101011100110000101011001010 0
b10001110 .
b10011110011100110000101011001010 1
b11100101011100110000101011001010 ,
1-
b10011110001100010100110000111100 $
b10011110001100010100110000111100 *
b10011110001100010100110000111100 3
b11100101011100110000101011001010 #
b11100101011100110000101011001010 )
b11100101011100110000101011001010 2
1"
#36600
b11001 (
#37000
0"
#37500
b11100101011100110000101011001010 !
b11100101011100110000101011001010 /
b1000101001011100110000110001010 4
b1111001011010001011110111110010 5
b1111001011010001011110111110010 0
b1101000 .
b1000101011010001011110111110010 1
b1111001011010001011110111110010 ,
0-
b1000101001011100110000110001010 $
b1000101001011100110000110001010 *
b1000101001011100110000110001010 3
b1111001011010001011110111110010 #
b1111001011010001011110111110010 )
b1111001011010001011110111110010 2
1"
#37600
b11010 (
#38000
0"
#38500
b1111001011010001011110111110010 !
b1111001011010001011110111110010 /
b1101100010010110011010011011000 4
0+
b100000110001001011001101000001 5
b11101100010010110011010011011000 0
b10010111 .
b100000010010110011010011011000 1
b11101100010010110011010011011000 ,
1-
b11101100010010110011010011011000 $
b11101100010010110011010011011000 *
b11101100010010110011010011011000 3
b100000110001001011001101000001 #
b100000110001001011001101000001 )
b100000110001001011001101000001 2
1"
#38600
b11011 (
#39000
0"
#39500
b11101100010010110011010011011000 !
b11101100010010110011010011011000 /
b1000100100010100001001010001001 4
b111100001000001111001101111000 5
b11000100100010100001001010011001 0
b10001 .
b111100000010100001001010011001 1
b11000100100010100001001010011001 ,
b11000100100010100001001010001001 $
b11000100100010100001001010001001 *
b11000100100010100001001010001001 3
b111100001000001111001101111000 #
b111100001000001111001101111000 )
b111100001000001111001101111000 2
1"
#39600
b11100 (
#40000
0"
#40500
b11000100100010100001001010011001 !
b11000100100010100001001010011001 /
b1011011000000100110010110110110 4
1+
b1110101110001010000110111101011 5
b1110101110001010000110111101011 0
b110101 .
b1011011010001010000110111101011 1
b1110101110001010000110111101011 ,
0-
b1011011000000100110010110110110 $
b1011011000000100110010110110110 *
b1011011000000100110010110110110 3
b1110101110001010000110111101011 #
b1110101110001010000110111101011 )
b1110101110001010000110111101011 2
1"
#40600
b11101 (
#41000
0"
#41500
b1110101110001010000110111101011 !
b1110101110001010000110111101011 /
b1010111000101010001001110101110 4
b1100011010010111111100111000110 5
b1100011010010111111100111000110 0
b11000 .
b1010111010010111111100111000110 1
b1100011010010111111100111000110 ,
b1010111000101010001001110101110 $
b1010111000101010001001110101110 *
b1010111000101010001001110101110 3
b1100011010010111111100111000110 #
b1100011010010111111100111000110 )
b1100011010010111111100111000110 2
1"
#41600
b11110 (
#42000
0"
#42500
b1100011010010111111100111000110 !
b1100011010010111111100111000110 /
b10101000011111101110100101010 4
b1011110011101010000001010111100 5
b11011110011101010000001010111100 0
b10010010 .
b10101011101010000001010111100 1
b11011110011101010000001010111100 ,
b10101000011111101110100101010 $
b10101000011111101110100101010 *
b10101000011111101110100101010 3
b11011110011101010000001010111100 #
b11011110011101010000001010111100 )
b11011110011101010000001010111100 2
1"
#42600
b11111 (
#43000
0"
#43500
b11011110011101010000001010111100 !
b11011110011101010000001010111100 /
b111000100101111011111001110001 4
0+
b101110101111001101000001011 5
b10111000100101111011111001110001 0
b1100110 .
b10000101000101111011111001110001 1
b10111000100101111011111001110001 ,
1-
b10111000100101111011111001110001 $
b10111000100101111011111001110001 *
b10111000100101111011111001110001 3
b10000101110101111001101000001011 #
b10000101110101111001101000001011 )
b10000101110101111001101000001011 2
1"
#43600
b0 (
#44000
0"
#44500
b10111000100101111011111001110001 !
b10111000100101111011111001110001 /
b100111111100100101010101001111 4
1+
b1000010111100100100000110000101 5
b1000010111100100100000110000101 0
b110110 .
b10100111011100100100000110000101 1
b1000010111100100100000110000101 ,
1%
b100111111100100101010101001111 $
b100111111100100101010101001111 *
b100111111100100101010101001111 3
b1000010111100100100000110000101 #
b1000010111100100100000110000101 )
b1000010111100100100000110000101 2
1"
#44600
b1 (
#45000
0"
#45500
b1000010111100100100000110000101 !
b1000010111100100100000110000101 /
b11101000001100011001100111010 4
1+
b11101110011000110000000111011 5
b10011101110010010100011010011110 0
b1 .
b10011101010010010100011010011110 1
b10011101110010010100011010011110 ,
b11101000001100011001100111010 $
b11101000001100011001100111010 *
b11101000001100011001100111010 3
b10011101110011000110000000111011 #
b10011101110011000110000000111011 )
b10011101110011000110000000111011 2
1"
#45600
b10 (
#46000
0"
#46500
b10011101110010010100011010011110 !
b10011101110010010100011010011110 /
b1010101010100100101100010101 4
b111111001000110011001001111110 5
b10111111001000110011001001111110 0
b1101001 .
b10001010001000110011001001111110 1
b10111111001000110011001001111110 ,
b1010101010100100101100010101 $
b1010101010100100101100010101 *
b1010101010100100101100010101 3
b10111111001000110011001001111110 #
b10111111001000110011001001111110 )
b10111111001000110011001001111110 2
1"
#46600
b11 (
#47000
0"
#47500
b10111111001000110011001001111110 !
b10111111001000110011001001111110 /
b1101100100111000100101111011001 4
b1111000110110011001101111110001 5
b1111000110110011001101111110001 0
b11000 .
b11101100010110011001101111110001 1
b1111000110110011001101111110001 ,
b1101100100111000100101111011001 $
b1101100100111000100101111011001 *
b1101100100111000100101111011001 3
b1111000110110011001101111110001 #
b1111000110110011001101111110001 )
b1111000110110011001101111110001 2
1"
#47600
b100 (
#48000
0"
#48500
b1111000110110011001101111110001 !
b1111000110110011001101111110001 /
b100110001101011111101101001100 4
1+
b110001001000110000011101100010 5
b110001001000110000011101100010 0
b10110 .
b10100110001000110000011101100010 1
b110001001000110000011101100010 ,
b100110001101011111101101001100 $
b100110001101011111101101001100 *
b100110001101011111101101001100 3
b110001001000110000011101100010 #
b110001001000110000011101100010 )
b110001001000110000011101100010 2
1"
#48600
b101 (
#49000
0"
#49500
b110001001000110000011101100010 !
b110001001000110000011101100010 /
b1000111101110011010000110001111 4
b1001111101000010101010110011111 5
b1001111101000010101010101100110 0
b10000 .
b11000111001000010101010101100110 1
b1001111101000010101010101100110 ,
b1000111101110011010000110001111 $
b1000111101110011010000110001111 *
b1000111101110011010000110001111 3
b1001111101000010101010110011111 #
b1001111101000010101010110011111 )
b1001111101000010101010110011111 2
1"
#49600
b110 (
#50000
0"
#50500
b1001111101000010101010101100110 !
b1001111101000010101010101100110 /
b1011011110011010110000010110111 4
b1111100011011011010100111111000 5
b1111100011011011010100111111000 0
b1000001 .
b1011011011011011010100111111000 1
b1111100011011011010100111111000 ,
0-
b11011011110011010110000010110111 $
b11011011110011010110000010110111 *
b11011011110011010110000010110111 3
b1111100011011011010100111111000 #
b1111100011011011010100111111000 )
b1111100011011011010100111111000 2
1"
#50600
b111 (
#51000
0"
#51500
b1111100011011011010100111111000 !
b1111100011011011010100111111000 /
b101110011111011001010001011100 4
1+
b1001111110001000101011010011111 5
b11001111110001000101011010011111 0
b1000011 .
b101110010001000101011010011111 1
b11001111110001000101011010011111 ,
b10101110011111011001010001011100 $
b10101110011111011001010001011100 *
b10101110011111011001010001011100 3
b11001111110001000101011010011111 #
b11001111110001000101011010011111 )
b11001111110001000101011010011111 2
1"
#51600
b1000 (
#52000
0"
#52500
b11001111110001000101011010011111 !
b11001111110001000101011010011111 /
b1000100110111100011011110001001 4
0+
b101101110010111100000001011011 5
b11000100110111100011011110001001 0
b101110 .
b10101101010111100011011110001001 1
b11000100110111100011011110001001 ,
1-
b1000100110111100011011110001001 $
b1000100110111100011011110001001 *
b1000100110111100011011110001001 3
b10101101110010111100000001011011 #
b10101101110010111100000001011011 )
b10101101110010111100000001011011 2
1"
#52600
b1001 (
#53000
0"
#53500
b11000100110111100011011110001001 !
b11000100110111100011011110001001 /
b1101000001000110011111011010000 4
b100100101011100011001001001001 5
b1101000001000110011111011010000 0
b10000111 .
b10100100001000110011111011010000 1
b1101000001000110011111011010000 ,
0-
b11101000001000110011111011010000 $
b11101000001000110011111011010000 *
b11101000001000110011111011010000 3
b10100100101011100011001001001001 #
b10100100101011100011001001001001 )
b10100100101011100011001001001001 2
1"
#53600
b1010 (
#54000
0"
#54500
b1101000001000110011111011010000 !
b1101000001000110011111011010000 /
b101000110001111111110001010001 4
1+
b1101011111111101100000011010111 5
b11101011111111101100000011010111 0
b10000110 .
b101000011111101100000011010111 1
b11101011111111101100000011010111 ,
b10101000110001111111110001010001 $
b10101000110001111111110001010001 *
b10101000110001111111110001010001 3
b11101011111111101100000011010111 #
b11101011111111101100000011010111 )
b11101011111111101100000011010111 2
1"
#54600
b1011 (
#55000
0"
#55500
b11101011111111101100000011010111 !
b11101011111111101100000011010111 /
b110000111010111111100001100 4
b1001011001000010010111110010110 5
b1001011001000010010111110010110 0
b10001010 .
b10000110001000010010111110010110 1
b1001011001000010010111110010110 ,
1-
b110000111010111111100001100 $
b110000111010111111100001100 *
b110000111010111111100001100 3
b1001011001000010010111110010110 #
b1001011001000010010111110010110 )
b1001011001000010010111110010110 2
1"
#55600
b1100 (
#56000
0"
#56500
b1001011001000010010111110010110 !
b1001011001000010010111110010110 /
0+
b1100100010101111110110111001000 4
b1100001001011001100111011000010 5
b11100100010101110011101010001101 0
b110 .
b11100001010101110011101010001101 1
b11100100010101110011101010001101 ,
b1100100010101111110110111001000 $
b1100100010101111110110111001000 *
b1100100010101111110110111001000 3
b11100001001011001100111011000010 #
b11100001001011001100111011000010 )
b11100001001011001100111011000010 2
1"
#56600
b1101 (
#57000
0"
#57500
b11100100010101110011101010001101 !
b11100100010101110011101010001101 /
1+
b11110111100101110110100111101 4
b111011100000100101101001110111 5
b10111011100000100101101001110111 0
b111010 .
b10011110000000100101101001110111 1
b10111011100000100101101001110111 ,
b11110111100101110110100111101 $
b11110111100101110110100111101 *
b11110111100101110110100111101 3
b10111011100000100101101001110111 #
b10111011100000100101101001110111 )
b10111011100000100101101001110111 2
1"
#57600
b1110 (
#58000
0"
#58500
b10111011100000100101101001110111 !
b10111011100000100101101001110111 /
b111111000001010000000001111110 4
0+
b1001000011001101101100010010 5
b111111000001010000000001111110 0
b1101100 .
b1001000001010000000001111110 1
b111111000001010000000001111110 ,
0-
b10111111000001010000000001111110 $
b10111111000001010000000001111110 *
b10111111000001010000000001111110 3
b1001000011001101101100010010 #
b1001000011001101101100010010 )
b1001000011001101101100010010 2
1"
#58600
b1111 (
#59000
0"
#59500
b111111000001010000000001111110 !
b111111000001010000000001111110 /
1+
b11100110110011110011100111001 4
b110110111001011000000101101101 5
b110110111001011000000101101101 0
b110100 .
b10011100011001011000000101101101 1
b110110111001011000000101101101 ,
1-
b11100110110011110011100111001 $
b11100110110011110011100111001 *
b11100110110011110011100111001 3
b110110111001011000000101101101 #
b110110111001011000000101101101 )
b110110111001011000000101101101 2
1"
#59600
b10000 (
#60000
0"
#60500
b110110111001011000000101101101 !
b110110111001011000000101101101 /
b1101001111010111111011011010011 4
0+
b1111110100101000111100011111 5
b1101001111010111111011011010011 0
b10110100 .
b1111011010111111011011010011 1
b1101001111010111111011011010011 ,
0-
b11101001111010111111011011010011 $
b11101001111010111111011011010011 *
b11101001111010111111011011010011 3
b1111110100101000111100011111 #
b1111110100101000111100011111 )
b1111110100101000111100011111 2
1"
#60600
b10001 (
#61000
0"
#61500
b1101001111010111111011011010011 !
b1101001111010111111011011010011 /
1+
b111100000101001000100001111000 4
b1000010110110010010111110000101 5
b1000010110110010010111011100001 0
b1101 .
b111100010110010010111011100001 1
b1000010110110010010111011100001 ,
b10111100000101001000100001111000 $
b10111100000101001000100001111000 *
b10111100000101001000100001111000 3
b1000010110110010010111110000101 #
b1000010110110010010111110000101 )
b1000010110110010010111110000101 2
1"
#61600
b10010 (
#62000
0"
#62500
b1000010110110010010111011100001 !
b1000010110110010010111011100001 /
b100100100010110100101101001001 4
1+
b101101110110100101100101011011 5
b101101110110100101100101011001 0
b10010 .
b10100100010110100101100101011001 1
b101101110110100101100101011001 ,
1-
b100100100010110100101101001001 $
b100100100010110100101101001001 *
b100100100010110100101101001001 3
b101101110110100101100101011011 #
b101101110110100101100101011011 )
b101101110110100101100101011011 2
1"
#62600
b10011 (
#63000
0"
#63500
b101101110110100101100101011001 !
b101101110110100101100101011001 /
b10101000011001010111100101010 4
1+
b11111111100101010111000111111 5
b10011111111100101010111000111111 0
b10101 .
b10010101011100101010111000111111 1
b10011111111100101010111000111111 ,
b10101000011001010111100101010 $
b10101000011001010111100101010 *
b10101000011001010111100101010 3
b10011111111100101010111000111111 #
b10011111111100101010111000111111 )
b10011111111100101010111000111111 2
1"
#63600
b10100 (
#64000
0"
#64500
b10011111111100101010111000111111 !
b10011111111100101010111000111111 /
0+
b1000011001111110011100010000110 4
b101100000101010110001101011000 5
b1000011001111110011100010000110 0
b101110 .
b101100001111110011100010000110 1
b1000011001111110011100010000110 ,
0-
b11000011001111110011100010000110 $
b11000011001111110011100010000110 *
b11000011001111110011100010000110 3
b101100000101010110001101011000 #
b101100000101010110001101011000 )
b101100000101010110001101011000 2
1"
#64600
b10101 (
#65000
0"
#65500
b1000011001111110011100010000110 !
b1000011001111110011100010000110 /
b1001110001011111111001010011100 4
0+
b1000111000110100000110010001110 5
b1001110001011111111001000110100 0
b1110 .
b11000111001011111111001000110100 1
b1001110001011111111001000110100 ,
b11001110001011111111001010011100 $
b11001110001011111111001010011100 *
b11001110001011111111001010011100 3
b11000111000110100000110010001110 #
b11000111000110100000110010001110 )
b11000111000110100000110010001110 2
1"
#65600
b10110 (
#66000
0"
#66500
b1001110001011111111001000110100 !
b1001110001011111111001000110100 /
b10011011111011011110000100110 4
1+
b1111101001101011001100111111010 5
b1111101001101011001100111111010 0
b11010100 .
b10011001101011001100111111010 1
b1111101001101011001100111111010 ,
b10010011011111011011110000100110 $
b10010011011111011011110000100110 *
b10010011011111011011110000100110 3
b1111101001101011001100111111010 #
b1111101001101011001100111111010 )
b1111101001101011001100111111010 2
1"
#66600
b10111 (
#67000
0"
