f_multiplier/mantissa_multiplier.v
`timescale 1ns/1ns

//unsigned_multiplier
//round to down
//GRS를 이용해서 rount to nearest even
module mantissa_multiplier #(
    parameter integer BIT_WIDTH = 23
) (
    input [BIT_WIDTH-1:0] in0,
    input [BIT_WIDTH-1:0] in1,
    output reg [BIT_WIDTH-1:0] out,
    output reg carry
);

reg [(BIT_WIDTH + 1) * 2  : 0] res;
reg [bit_cnt_func(BIT_WIDTH+1)-1:0] i;
reg [1:0] flag_zero;
reg mantissa_last;
reg G,R,S;
localparam BOTH_ZERO=2'b11;
localparam EITHER_ZERO_LEFT=2'b10;
localparam EITHER_ZERO_RIGHT=2'b01;
localparam NITHER_ZERO=2'b00;
always@(*)begin
    flag_zero = (in0 == 0 && in1 == 0) ? BOTH_ZERO : (in0 == 0  ? EITHER_ZERO_LEFT : (in1 == 0 ? EITHER_ZERO_RIGHT : NITHER_ZERO));
    //to avoid latch
    res = {(BIT_WIDTH * 2 + 2){1'b0}};
    //set 1.xxxxxxx...
    res[BIT_WIDTH:0] = {1'b1,in1};

    for(i = BIT_WIDTH+1; i > 0; i = i - 1'b1)begin
        
        if(res[0]) res[(BIT_WIDTH+1) * 2 -: (BIT_WIDTH + 2)] = res[(BIT_WIDTH+1) * 2 -: (BIT_WIDTH + 2)] + {2'b01,in0};

        res = res >>1;
        carry = res[(BIT_WIDTH+1)*2-1];
    end
    
    if(carry)begin
        mantissa_last=res[BIT_WIDTH+1];
        G=res[BIT_WIDTH];
        R=res[BIT_WIDTH-1];
        S=|res[BIT_WIDTH-2:0];
       
    end else begin
        mantissa_last=res[BIT_WIDTH];
        G=res[BIT_WIDTH-1];
        R=res[BIT_WIDTH-2];
        S=|res[BIT_WIDTH-3:0];
    
    end 

    case ({G,R,S})
        3'b000:begin
            //round down(do nothing)
        end 
        3'b001:begin
            //round down(do nothing)
        end 
        3'b010:begin
            //round down(do nothing)
        end 
        3'b011:begin
            //round down(do nothing)
        end 
        3'b100:begin
            if(mantissa_last)begin
                res[(BIT_WIDTH+1) * 2 -: (BIT_WIDTH + 2)] = res[(BIT_WIDTH+1) * 2 -: (BIT_WIDTH + 2)] + 1'b1;
                //round up case
            end
            //round down(do nothing)
        end 
        3'b101:begin
            res[(BIT_WIDTH+1) * 2 -: (BIT_WIDTH + 2)] = res[(BIT_WIDTH+1) * 2 -: (BIT_WIDTH + 2)] + 1'b1;
            
        end 
        3'b110:begin
            res[(BIT_WIDTH+1) * 2 -: (BIT_WIDTH + 2)] = res[(BIT_WIDTH+1) * 2 -: (BIT_WIDTH + 2)] + 1'b1;
            
        end 
        3'b111:begin
            res[(BIT_WIDTH+1) * 2 -: (BIT_WIDTH + 2)] = res[(BIT_WIDTH+1) * 2 -: (BIT_WIDTH + 2)] + 1'b1;
            
        end 
        default:begin
            //do noting 
        end
         
    endcase
    if(flag_zero==BOTH_ZERO) out = 0;
    else if(flag_zero==EITHER_ZERO_RIGHT) out= in0[BIT_WIDTH-1:0];
    else if(flag_zero==EITHER_ZERO_LEFT) out= in1[BIT_WIDTH-1:0]; 
    else if(carry) out = res[((BIT_WIDTH + 1) * 2 -2)  -: (BIT_WIDTH)];
    else out = res[((BIT_WIDTH + 1) * 2 -3)  -: (BIT_WIDTH)];
//BIT_WIDTH * 2 + 1 -: (BIT_WIDTH+1) 여기부터 시작하면 carry시에 값을 날려버리는 현상이 존재한다
//당연한건데 이딴걸 못보고 븅순..
// 어차피 캐리 밀어버려서 BIT_WIDTH*2 + 2 해도 ㄱㅊ
    
end


//verilog에서 이게 한계다 변수 추가를 하는건 불가능함 ㅋㅋ
function integer bit_cnt_func;
    input integer bitwith;
    for(bit_cnt_func = 0;bitwith>0;bitwith= bitwith/2) bit_cnt_func=bit_cnt_func+1;
    //3비트의 signicant 를 받았다면 1번 더 해야하니까 한번 더 더해줌 ㅋ
endfunction
endmodule

f_multiplier/f_multiplier.v
`timescale 1ns/1ns
`include "mantissa_multiplier.v"

module f_multiplier (
    input clk,
    input rstn,
    input [31:0] in0,
    input [31:0] in1,
    output reg [31:0] out
);

reg [31:0] res;
wire [22:0] fraction;
wire flag_carry;
localparam FLOAT_32_BIAS = 8'h7f; //127 
localparam FRACTION_BIT_WIDTH=23;
mantissa_multiplier#(
    .BIT_WIDTH(23)
) u_mantissa_multiplier(
    .in0(in0[FRACTION_BIT_WIDTH-1:0]),
    .in1(in1[FRACTION_BIT_WIDTH-1:0]),
    .out(fraction),
    .carry(flag_carry)
);

always @(posedge clk or negedge rstn)begin
    if(!rstn) begin
        out <= {32{1'b0}};
    end else begin
        //1 cycle delay..
        out <= res;
    end

end

always @(*) begin
    res={32{1'b0}};
    res[31]= in0[31] ^ in1[31]; //assign sign shit~
    res[30:23] = (in0[30:23]-FLOAT_32_BIAS) + (in1[30:23]-FLOAT_32_BIAS) + FLOAT_32_BIAS; //overflow때문에 미리 이렇게 처리 해야 한다능 ㅎ 
    
    if(flag_carry==1'b1) 
        res[30:23]=res[30:23]+{{7{1'b0}},flag_carry};
    
    res[22:0]=fraction;
end


//func은 조합회로 모델링에 사용이 가능하다.. 라능거.

endmodule

f_multiplier/f_multiplier_tb.v
`timescale 1ns/1ns
`include "f_multiplier.v"
module f_multiplier_tb;

localparam BIT_WIDTH=32;
reg clk,rstn;
reg [BIT_WIDTH-1:0] in0,in1;
wire [BIT_WIDTH-1:0] out;

f_multiplier u_f_multiplier(
    .clk(clk),
    .rstn(rstn),
    .in0(in0),
    .in1(in1),
    .out(out)
);

always #5 clk = ~clk;
integer i;
integer f;
initial begin
    $dumpfile("f_multiplier.vcd");
    $dumpvars(0);
end

initial begin
    f = $fopen("f_multiplier_log.txt");
    $display("init val... [%0d]\n",$time);
    rstn = 0;
    clk = 0;
    in0 = 0;
    in1 = 0;
    $display("reset...![%0d]\n",$time);
    #100
        rstn = 0;
    #10
        rstn = 1;
    #10
    $display("push random data..[%0d]\n",$time);
    for(i=0;i<1024;i++)begin
        @(posedge clk);
        in0=$random;
        in1=$random;
        #50
        $fwrite(f,"%b\n",in0);
        $fwrite(f,"%b\n",in1);
        $fwrite(f,"%b\n",out);
    end
    #100 $fwrite(f,"quit!");
    $finish;

    
end


    
endmodule

f_multiplier/f_multiplier.vcd
$date
	Wed Dec  7 20:34:33 2022
$end
$version
	Icarus Verilog
$end
$timescale
	1ns
$end
$scope module f_multiplier_tb $end
$var wire 32 ! out [31:0] $end
$var reg 1 " clk $end
$var reg 32 # in0 [31:0] $end
$var reg 32 $ in1 [31:0] $end
$var reg 1 % rstn $end
$var integer 32 & f [31:0] $end
$var integer 32 ' i [31:0] $end
$scope module u_f_multiplier $end
$var wire 1 " clk $end
$var wire 32 ( in0 [31:0] $end
$var wire 32 ) in1 [31:0] $end
$var wire 1 % rstn $end
$var wire 23 * fraction [22:0] $end
$var wire 1 + flag_carry $end
$var reg 32 , out [31:0] $end
$var reg 32 - res [31:0] $end
$scope module u_mantissa_multiplier $end
$var wire 23 . in0 [22:0] $end
$var wire 23 / in1 [22:0] $end
$var reg 1 + carry $end
$var reg 2 0 flag_zero [1:0] $end
$var reg 5 1 i [4:0] $end
$var reg 23 2 out [22:0] $end
$var reg 49 3 res [48:0] $end
$scope function bit_cnt_func $end
$var integer 32 4 bitwith [31:0] $end
$upscope $end
$upscope $end
$upscope $end
$upscope $end
$enddefinitions $end
#0
$dumpvars
bx 4
b10000000000000000000000000000000000000000000000 3
b0 2
b0 1
b11 0
b0 /
b0 .
b1000000100000000000000000000000 -
b0 ,
0+
b0 *
b0 )
b0 (
bx '
b10 &
0%
b0 $
b0 #
0"
b0 !
$end
#5
1"
#10
0"
#15
1"
#20
0"
#25
1"
#30
0"
#35
1"
#40
0"
#45
1"
#50
0"
#55
1"
#60
0"
#65
1"
#70
0"
#75
1"
#80
0"
#85
1"
#90
0"
#95
1"
#100
0"
#105
1"
#110
0"
1%
#115
b1000000100000000000000000000000 !
b1000000100000000000000000000000 ,
1"
#120
0"
b0 '
#125
b1000000010000100001001 *
b1000000010000100001001 2
0+
b0 1
b10100000001000010000100111101101111111100100100 3
b0 0
b10010101111010000001 /
b10010011001000000010000100001001 -
b101010011010100100100 .
b11000000100010010101111010000001 $
b11000000100010010101111010000001 )
b10010000101010011010100100100 #
b10010000101010011010100100100 (
1"
#130
0"
#135
b10010011001000000010000100001001 !
b10010011001000000010000100001001 ,
1"
#140
0"
#145
1"
#150
0"
#155
1"
#160
0"
#165
1"
#170
0"
#175
b11110010110101011110111 *
b11110010110101011110111 2
b0 1
b11111001011010101111011101101011100101101111011 3
b11100000101011001100011 /
b1110110111110010110101011110111 -
b1001101011000001001 .
b10110001111100000101011001100011 $
b10110001111100000101011001100011 )
b10000100100001001101011000001001 #
b10000100100001001101011000001001 (
1"
b1 '
#180
0"
#185
b1110110111110010110101011110111 !
b1110110111110010110101011110111 ,
1"
#190
0"
#195
1"
#200
0"
#205
1"
#210
0"
#215
1"
#220
0"
#225
b1000100000000101110001 *
b1000100000000101110001 2
1+
b0 1
b101000100000000101110001000001101000101100101001 3
b10111111001100110001101 /
b1110001000100000000101110001 -
b1110010111101100001101 .
b1000110110111111001100110001101 $
b1000110110111111001100110001101 )
b110101110010111101100001101 #
b110101110010111101100001101 (
1"
b10 '
#230
0"
#235
b1110001000100000000101110001 !
b1110001000100000000101110001 ,
1"
#240
0"
#245
1"
#250
0"
#255
1"
#260
0"
#265
1"
#270
0"
#275
b10110100101100000000 *
b10110100101100000000 2
1+
b0 1
b100010110100101100000000010010001010100100011010 3
b1101110101001000010010 /
b1111100100010110100101100000000 -
b10000101000010001100101 .
b10001001001101110101001000010010 $
b10001001001101110101001000010010 )
b10110010110000101000010001100101 #
b10110010110000101000010001100101 (
1"
b11 '
#280
0"
#285
b1111100100010110100101100000000 !
b1111100100010110100101100000000 ,
1"
#290
0"
#295
1"
#300
0"
#305
1"
#310
0"
#315
1"
#320
0"
#325
b10011011001011011111111 *
b10011011001011011111111 2
1+
b0 1
b110011011001011011111111000000010101010000001101 3
b10101111100110100001101 /
b1001000010011011001011011111111 -
b11100111110001100000001 .
b110110101111100110100001101 $
b110110101111100110100001101 )
b111100111110001100000001 #
b111100111110001100000001 (
1"
b100 '
#330
0"
#335
b1001000010011011001011011111111 !
b1001000010011011001011011111111 ,
1"
#340
0"
#345
1"
#350
0"
#355
1"
#360
0"
#365
1"
#370
0"
#375
b1101011001111011011010 *
b1101011001111011011010 2
0+
b0 1
b10110101100111101101101011010100000011100011110 3
b11011100110100111101 /
b11010001101011001111011011010 -
b1000111111000101110110 .
b11110100011011100110100111101 $
b11110100011011100110100111101 )
b111011001000111111000101110110 #
b111011001000111111000101110110 (
1"
b101 '
#380
0"
#385
b11010001101011001111011011010 !
b11010001101011001111011011010 ,
1"
#390
0"
#395
1"
#400
0"
#405
1"
#410
0"
#415
1"
#420
0"
#425
b100000100110011000000 *
b100000100110011000000 2
1+
b0 1
b100100000100110011000000000111101100000010011100 3
b1011011111011110001100 /
b1111101100100000100110011000000 -
b10101000101011111101101 .
b1000110001011011111011110001100 $
b1000110001011011111011110001100 )
b1110110110101000101011111101101 #
b1110110110101000101011111101101 (
1"
b110 '
#430
0"
#435
b1111101100100000100110011000000 !
b1111101100100000100110011000000 ,
1"
#440
0"
#445
1"
#450
0"
#455
1"
#460
0"
#465
1"
#470
0"
#475
b1101011010011010111010 *
b1101011010011010111010 2
1+
b0 1
b101101011010011010111010010010001111101010010110 3
b1101110010010011000110 /
b10100000101101011010011010111010 -
b11111011110100111111001 .
b11100011001101110010010011000110 $
b11100011001101110010010011000110 )
b1111100111111011110100111111001 #
b1111100111111011110100111111001 (
1"
b111 '
#480
0"
#485
b10100000101101011010011010111010 !
b10100000101101011010011010111010 ,
1"
#490
0"
#495
1"
#500
0"
#505
1"
#510
0"
#515
1"
#520
0"
#525
b11101110110011101100 *
b11101110110011101100 2
1+
b0 1
b100011101110110011101100011001101100010011010010 3
b100111101001010101010 /
b1111000100011101110110011101100 -
b11101111000010011000101 .
b11010101000100111101001010101010 $
b11010101000100111101001010101010 )
b11100010111101111000010011000101 #
b11100010111101111000010011000101 (
1"
b1000 '
#530
0"
#535
b1111000100011101110110011101100 !
b1111000100011101110110011101100 ,
1"
#540
0"
#545
1"
#550
0"
#555
1"
#560
0"
#565
1"
#570
0"
#575
b100001010100000001000 *
b100001010100000001000 2
1+
b0 1
b100100001010100000001000000010100011010101110011 3
b10100100111001001110111 /
b11101111000100001010100000001000 -
b1011111111011111100101 .
b10111011110100100111001001110111 $
b10111011110100100111001001110111 )
b1110010101011111111011111100101 #
b1110010101011111111011111100101 (
1"
b1001 '
#580
0"
#585
b11101111000100001010100000001000 !
b11101111000100001010100000001000 ,
1"
#590
0"
#595
1"
#600
0"
#605
1"
#610
0"
#615
1"
#620
0"
#625
b1001010111011010111001 *
b1001010111011010111001 2
1+
b0 1
b101001010111011010111001100111101111101000001110 3
b11011001101101110001111 /
b10010001101001010111011010111001 -
b1100101101011000010010 .
b1000111111011001101101110001111 $
b1000111111011001101101110001111 )
b10001001001100101101011000010010 #
b10001001001100101101011000010010 (
1"
b1010 '
#630
0"
#635
b10010001101001010111011010111001 !
b10010001101001010111011010111001 ,
1"
#640
0"
#645
1"
#650
0"
#655
1"
#660
0"
#665
1"
#670
0"
#675
b1010011110110110111010 *
b1010011110110110111010 2
1+
b0 1
b101010011110110110111010100101010000110010111100 3
b11101101001011011001110 /
b10100001001010011110110110111010 -
b1100000110100111110010 .
b11100111011101101001011011001110 $
b11100111011101101001011011001110 )
b1111001001100000110100111110010 #
b1111001001100000110100111110010 (
1"
b1011 '
#680
0"
#685
b10100001001010011110110110111010 !
b10100001001010011110110110111010 ,
1"
#690
0"
#695
1"
#700
0"
#705
1"
#710
0"
#715
1"
#720
0"
#725
b10010110001000100000110 *
b10010110001000100000110 2
0+
b0 1
b11001011000100010000011011000010100010010001000 3
b10010100100111011000101 /
b10111010010110001000100000110 -
b111101011101000 .
b11100010110010100100111011000101 $
b11100010110010100100111011000101 )
b11110100000000000111101011101000 #
b11110100000000000111101011101000 (
1"
b1100 '
#730
0"
#735
b10111010010110001000100000110 !
b10111010010110001000100000110 ,
1"
#740
0"
#745
1"
#750
0"
#755
1"
#760
0"
#765
1"
#770
0"
#775
b11100000011011000111000 *
b11100000011011000111000 2
0+
b0 1
b11110000001101100011100001011001000100011101100 3
b11100010100010111101 /
b11001101011100000011011000111000 -
b10110000100100101011100 .
b11011110100011100010100010111101 $
b11011110100011100010100010111101 )
b101110010110000100100101011100 #
b101110010110000100100101011100 (
1"
b1101 '
#780
0"
#785
b11001101011100000011011000111000 !
b11001101011100000011011000111000 ,
1"
#790
0"
#795
1"
#800
0"
#805
1"
#810
0"
#815
1"
#820
0"
#825
b10111111100000001110000 *
b10111111100000001110000 2
0+
b0 1
b11011111110000000111000000010110111011111000001 3
b1001110010011001100101 /
b1001110111111100000001110000 -
b1010110101100000101101 .
b10110010101001110010011001100101 $
b10110010101001110010011001100101 )
b10010110101010110101100000101101 #
b10010110101010110101100000101101 (
1"
b1110 '
#830
0"
#835
b1001110111111100000001110000 !
b1001110111111100000001110000 ,
1"
#840
0"
#845
1"
#850
0"
#855
1"
#860
0"
#865
1"
#870
0"
#875
b11000111011100010101010 *
b11000111011100010101010 2
1+
b0 1
b111000111011100010101010001101010000110011011110 3
b11100111000011100001010 /
b11110111111000111011100010101010 -
b11011110110001001100011 .
b101011100111000011100001010 $
b101011100111000011100001010 )
b10110001111011110110001001100011 #
b10110001111011110110001001100011 (
1"
b1111 '
#880
0"
#885
b11110111111000111011100010101010 !
b11110111111000111011100010101010 ,
1"
#890
0"
#895
1"
#900
0"
#905
1"
#910
0"
#915
1"
#920
0"
#925
b1001101100001011110000 *
b1001101100001011110000 2
1+
b0 1
b101001101100001011110000110101101101000000000000 3
b11001000010000100100000 /
b10010001001001101100001011110000 -
b1110110010001010000000 .
b10000011001000010000100100000 $
b10000011001000010000100100000 )
b11000000001110110010001010000000 #
b11000000001110110010001010000000 (
1"
b10000 '
#930
0"
#935
b10010001001001101100001011110000 !
b10010001001001101100001011110000 ,
1"
#940
0"
#945
1"
#950
0"
#955
1"
#960
0"
#965
1"
#970
0"
#975
b10001101001110111110011 *
b10001101001110111110011 2
1+
b0 1
b110001101001110111110011001111100011000101000010 3
b10011001100110010011101 /
b11100100110001101001110111110011 -
b11110000100010110101010 .
b11001110110011001100110010011101 $
b11001110110011001100110010011101 )
b1010101011110000100010110101010 #
b1010101011110000100010110101010 (
1"
b10001 '
#980
0"
#985
b11100100110001101001110111110011 !
b11100100110001101001110111110011 ,
1"
#990
0"
#995
1"
#1000
0"
#1005
1"
#1010
0"
#1015
1"
#1020
0"
#1025
b1001001110011001111111 *
b1001001110011001111111 2
0+
b0 1
b10100100111001100111111101000100111010100100010 3
b111011100000010011 /
b10101001001001110011001111111 -
b1000000011111010010110 .
b10001001100000111011100000010011 $
b10001001100000111011100000010011 )
b11001011001000000011111010010110 #
b11001011001000000011111010010110 (
1"
b10010 '
#1030
0"
#1035
b10101001001001110011001111111 !
b10101001001001110011001111111 ,
1"
#1040
0"
#1045
1"
#1050
0"
#1055
1"
#1060
0"
#1065
1"
#1070
0"
#1075
b11101101100110001001000 *
b11101101100110001001000 2
0+
b0 1
b11110110110011000100100010111000000101000110111 3
b1001111101011001010011 /
b1110000111101101100110001001000 -
b1111000011100000001101 .
b10101001101001111101011001010011 $
b10101001101001111101011001010011 )
b10000110101111000011100000001101 #
b10000110101111000011100000001101 (
1"
b10011 '
#1080
0"
#1085
b1110000111101101100110001001000 !
b1110000111101101100110001001000 ,
1"
#1090
0"
#1095
1"
#1100
0"
#1105
1"
#1110
0"
#1115
1"
#1120
0"
#1125
b10011111000100010100101 *
b10011111000100010100101 2
0+
b0 1
b11001111100010001010010101110001100100000000111 3
b1001100010101011010101 /
b11100000110011111000100010100101 -
b111111101110101101011 .
b11101010101001100010101011010101 $
b11101010101001100010101011010101 )
b110101100111111101110101101011 #
b110101100111111101110101101011 (
1"
b10100 '
#1130
0"
#1135
b11100000110011111000100010100101 !
b11100000110011111000100010100101 ,
1"
#1140
0"
#1145
1"
#1150
0"
#1155
1"
#1160
0"
#1165
1"
#1170
0"
#1175
b11111010011100111010000 *
b11111010011100111010000 2
0+
b0 1
b11111101001110011101000011011001100100101011100 3
b10101100011111010101110 /
b11000111111010011100111010000 -
b101110100101000000010 .
b11010111010101100011111010101110 $
b11010111010101100011111010101110 )
b10000001000101110100101000000010 #
b10000001000101110100101000000010 (
1"
b10101 '
#1180
0"
#1185
b11000111111010011100111010000 !
b11000111111010011100111010000 ,
1"
#1190
0"
#1195
1"
#1200
0"
#1205
1"
#1210
0"
#1215
1"
#1220
0"
#1225
b10001010110000100101000 *
b10001010110000100101000 2
1+
b0 1
b110001010110000100101000000011010110100001110011 3
b10001010111001011001111 /
b10110111010001010110000100101000 -
b11111111110100100011101 .
b11100111110001010111001011001111 $
b11100111110001010111001011001111 )
b1110111111111110100100011101 #
b1110111111111110100100011101 (
1"
b10110 '
#1230
0"
#1235
b10110111010001010110000100101000 !
b10110111010001010110000100101000 ,
1"
#1240
0"
#1245
1"
#1250
0"
#1255
1"
#1260
0"
#1265
1"
#1270
0"
#1275
b11011111111010110011 *
b11011111111010110011 2
0+
b0 1
b10001101111111101011001110000001010101001011110 3
b10010110010100001010 /
b1010111000011011111111010110011 -
b1000100100100100011 .
b101000010010110010100001010 $
b101000010010110010100001010 )
b10001100001000100100100100011 #
b10001100001000100100100100011 (
1"
b10111 '
#1280
0"
#1285
b1010111000011011111111010110011 !
b1010111000011011111111010110011 ,
1"
#1290
0"
#1295
1"
#1300
0"
#1305
1"
#1310
0"
#1315
1"
#1320
0"
#1325
b1010000101001011010101 *
b1010000101001011010101 2
1+
b0 1
b101010000101001011010101110101000111111101011000 3
b1100010100110000111100 /
b1000100001010000101001011010101 -
b11100110000101011001010 .
b10011110001100010100110000111100 $
b10011110001100010100110000111100 )
b11100101011100110000101011001010 #
b11100101011100110000101011001010 (
1"
b11000 '
#1330
0"
#1335
b1000100001010000101001011010101 !
b1000100001010000101001011010101 ,
1"
#1340
0"
#1345
1"
#1350
0"
#1355
1"
#1360
0"
#1365
1"
#1370
0"
#1375
b111101000100111000111 *
b111101000100111000111 2
1+
b0 1
b100111101000100111000111111010110001011001110100 3
b1011100110000110001010 /
b1111111000111101000100111000111 -
b11010001011110111110010 .
b1000101001011100110000110001010 $
b1000101001011100110000110001010 )
b1111001011010001011110111110010 #
b1111001011010001011110111110010 (
1"
b11001 '
#1380
0"
#1385
b1111111000111101000100111000111 !
b1111111000111101000100111000111 ,
1"
#1390
0"
#1395
1"
#1400
0"
#1405
1"
#1410
0"
#1415
1"
#1420
0"
#1425
b111000010001010111110 *
b111000010001010111110 2
1+
b0 1
b100111000010001010111110111010110111001011011000 3
b10010110011010011011000 /
b11001101100111000010001010111110 -
b10001001011001101000001 .
b11101100010010110011010011011000 $
b11101100010010110011010011011000 )
b100000110001001011001101000001 #
b100000110001001011001101000001 (
1"
b11010 '
#1430
0"
#1435
b11001101100111000010001010111110 !
b11001101100111000010001010111110 ,
1"
#1440
0"
#1445
1"
#1450
0"
#1455
1"
#1460
0"
#1465
1"
#1470
0"
#1475
b1011011001110111001011 *
b1011011001110111001011 2
0+
b0 1
b10101101100111011100101111100001011101100111000 3
b10100001001010001001 /
b11000001001011011001110111001011 -
b1000001111001101111000 .
b11000100100010100001001010001001 $
b11000100100010100001001010001001 )
b111100001000001111001101111000 #
b111100001000001111001101111000 (
1"
b11011 '
#1480
0"
#1485
b11000001001011011001110111001011 !
b11000001001011011001110111001011 ,
1"
#1490
0"
#1495
1"
#1500
0"
#1505
1"
#1510
0"
#1515
1"
#1520
0"
#1525
b10010001011111010110111 *
b10010001011111010110111 2
0+
b0 1
b11001000101111101011011111010111001110000010010 3
b100110010110110110 /
b10001010010001011111010110111 -
b10001010000110111101011 .
b1011011000000100110010110110110 $
b1011011000000100110010110110110 )
b1110101110001010000110111101011 #
b1110101110001010000110111101011 (
1"
b11100 '
#1530
0"
#1535
b10001010010001011111010110111 !
b10001010010001011111010110111 ,
1"
#1540
0"
#1545
1"
#1550
0"
#1555
1"
#1560
0"
#1565
1"
#1570
0"
#1575
b11011011001000000011100 *
b11011011001000000011100 2
0+
b0 1
b11101101100100000001110011010110111011010010100 3
b101010001001110101110 /
b1111010111011011001000000011100 -
b10010111111100111000110 .
b1010111000101010001001110101110 $
b1010111000101010001001110101110 )
b1100011010010111111100111000110 #
b1100011010010111111100111000110 (
1"
b11101 '
#1580
0"
#1585
b1111010111011011001000000011100 !
b1111010111011011001000000011100 ,
1"
#1590
0"
#1595
1"
#1600
0"
#1605
1"
#1610
0"
#1615
1"
#1620
0"
#1625
b10011011000000110010 *
b10011011000000110010 2
1+
b0 1
b100010011011000000110010100100101011111011011000 3
b11111101110100101010 /
b10110100000010011011000000110010 -
b11101010000001010111100 .
b10101000011111101110100101010 $
b10101000011111101110100101010 )
b11011110011101010000001010111100 #
b11011110011101010000001010111100 (
1"
b11110 '
#1630
0"
#1635
b10110100000010011011000000110010 !
b10110100000010011011000000110010 ,
1"
#1640
0"
#1645
1"
#1650
0"
#1655
1"
#1660
0"
#1665
1"
#1670
0"
#1675
b11111111001100001111111 *
b11111111001100001111111 2
0+
b0 1
b11111111100110000111111111111000010100011011011 3
b101111011111001110001 /
b1111110111111111001100001111111 -
b10101111001101000001011 .
b10111000100101111011111001110001 $
b10111000100101111011111001110001 )
b10000101110101111001101000001011 #
b10000101110101111001101000001011 (
1"
b11111 '
#1680
0"
#1685
b1111110111111111001100001111111 !
b1111110111111111001100001111111 ,
1"
#1690
0"
#1695
1"
#1700
0"
#1705
1"
#1710
0"
#1715
1"
#1720
0"
#1725
b11001010101001010101010 *
b11001010101001010101010 2
1+
b0 1
b111001010101001010101010001111010110000100001011 3
b11100100101010101001111 /
b101011011001010101001010101010 -
b11100100100000110000101 .
b100111111100100101010101001111 $
b100111111100100101010101001111 )
b1000010111100100100000110000101 #
b1000010111100100100000110000101 (
1"
b100000 '
#1730
0"
#1735
b101011011001010101001010101010 !
b101011011001010101001010101010 ,
1"
#1740
0"
#1745
1"
#1750
0"
#1755
1"
#1760
0"
#1765
1"
#1770
0"
#1775
b10101100100011010001000 *
b10101100100011010001000 2
0+
b0 1
b11010110010001101000100010110111000111001011110 3
b1100011001100111010 /
b11111011010101100100011010001000 -
b10011000110000000111011 .
b11101000001100011001100111010 $
b11101000001100011001100111010 )
b10011101110011000110000000111011 #
b10011101110011000110000000111011 (
1"
b100001 '
#1780
0"
#1785
b11111011010101100100011010001000 !
b11111011010101100100011010001000 ,
1"
#1790
0"
#1795
1"
#1800
0"
#1805
1"
#1810
0"
#1815
1"
#1820
0"
#1825
b10110010001111011001001 *
b10110010001111011001001 2
b0 1
b11011001000111101100100110110100000111001010110 3
b1010100100101100010101 /
b10001010010110010001111011001001 -
b1000110011001001111110 .
b1010101010100100101100010101 $
b1010101010100100101100010101 )
b10111111001000110011001001111110 #
b10111111001000110011001001111110 (
1"
b100010 '
#1830
0"
#1835
b10001010010110010001111011001001 !
b10001010010110010001111011001001 ,
1"
#1840
0"
#1845
1"
#1850
0"
#1855
1"
#1860
0"
#1865
1"
#1870
0"
#1875
b1001101101110000000 *
b1001101101110000000 2
1+
b0 1
b100001001101101110000000000000001100101001001001 3
b111000100101111011001 /
b100110000001001101101110000000 -
b10110011001101111110001 .
b1101100100111000100101111011001 $
b1101100100111000100101111011001 )
b1111000110110011001101111110001 #
b1111000110110011001101111110001 (
1"
b100011 '
#1880
0"
#1885
b100110000001001101101110000000 !
b100110000001001101101110000000 ,
1"
#1890
0"
#1895
1"
#1900
0"
#1905
1"
#1910
0"
#1915
1"
#1920
0"
#1925
b11001111100100010000001 *
b11001111100100010000001 2
0+
b0 1
b11100111110010001000000111011010100011100011000 3
b1101011111101101001100 /
b10111111001111100100010000001 -
b1000110000011101100010 .
b100110001101011111101101001100 $
b100110001101011111101101001100 )
b110001001000110000011101100010 #
b110001001000110000011101100010 (
1"
b100100 '
#1930
0"
#1935
b10111111001111100100010000001 !
b10111111001111100100010000001 ,
1"
#1940
0"
#1945
1"
#1950
0"
#1955
1"
#1960
0"
#1965
1"
#1970
0"
#1975
b11010011111100101100001 *
b11010011111100101100001 2
0+
b0 1
b11101001111110010110000110111101101001011010001 3
b1110011010000110001111 /
b1010111111010011111100101100001 -
b1000010101010110011111 .
b1000111101110011010000110001111 $
b1000111101110011010000110001111 )
b1001111101000010101010110011111 #
b1001111101000010101010110011111 (
1"
b100101 '
#1980
0"
#1985
b1010111111010011111100101100001 !
b1010111111010011111100101100001 ,
1"
#1990
0"
#1995
1"
#2000
0"
#2005
1"
#2010
0"
#2015
1"
#2020
0"
#2025
b1111101010101011100101 *
b1111101010101011100101 2
1+
b0 1
b101111101010101011100101001110011000000001001000 3
b10011010110000010110111 /
b10011000101111101010101011100101 -
b11011011010100111111000 .
b11011011110011010110000010110111 $
b11011011110011010110000010110111 )
b1111100011011011010100111111000 #
b1111100011011011010100111111000 (
1"
b100110 '
#2030
0"
#2035
b10011000101111101010101011100101 !
b10011000101111101010101011100101 ,
1"
#2040
0"
#2045
1"
#2050
0"
#2055
1"
#2060
0"
#2065
1"
#2070
0"
#2075
b10000100111101101100011 *
b10000100111101101100011 2
1+
b0 1
b110000100111101101100011110001100000110100100100 3
b11111011001010001011100 /
b111110110000100111101101100011 -
b10001000101011010011111 .
b10101110011111011001010001011100 $
b10101110011111011001010001011100 )
b11001111110001000101011010011111 #
b11001111110001000101011010011111 (
1"
b100111 '
#2080
0"
#2085
b111110110000100111101101100011 !
b111110110000100111101101100011 ,
1"
#2090
0"
#2095
1"
#2100
0"
#2105
1"
#2110
0"
#2115
1"
#2120
0"
#2125
b1100001101110100000010 *
b1100001101110100000010 2
1+
b0 1
b101100001101110100000010010001110111110110110011 3
b10111100011011110001001 /
b10110011001100001101110100000010 -
b10010111100000001011011 .
b1000100110111100011011110001001 $
b1000100110111100011011110001001 )
b10101101110010111100000001011011 #
b10101101110010111100000001011011 (
1"
b101000 '
#2130
0"
#2135
b10110011001100001101110100000010 !
b10110011001100001101110100000010 ,
1"
#2140
0"
#2145
1"
#2150
0"
#2155
1"
#2160
0"
#2165
1"
#2170
0"
#2175
b10111100010100110000100 *
b10111100010100110000100 2
0+
b0 1
b11011110001010011000010001100011000100101010000 3
b1000110011111011010000 /
b1001101010111100010100110000100 -
b1011100011001001001001 .
b11101000001000110011111011010000 $
b11101000001000110011111011010000 )
b10100100101011100011001001001001 #
b10100100101011100011001001001001 (
1"
b101001 '
#2180
0"
#2185
b1001101010111100010100110000100 !
b1001101010111100010100110000100 ,
1"
#2190
0"
#2195
1"
#2200
0"
#2205
1"
#2210
0"
#2215
1"
#2220
0"
#2225
b10001110000001011111101 *
b10001110000001011111101 2
1+
b0 1
b110001110000001011111101100011111010100000000111 3
b10001111111110001010001 /
b1010101010001110000001011111101 -
b11111101100000011010111 .
b10101000110001111111110001010001 $
b10101000110001111111110001010001 )
b11101011111111101100000011010111 #
b11101011111111101100000011010111 (
1"
b101010 '
#2230
0"
#2235
b1010101010001110000001011111101 !
b1010101010001110000001011111101 ,
1"
#2240
0"
#2245
1"
#2250
0"
#2255
1"
#2260
0"
#2265
1"
#2270
0"
#2275
b10001100101010001011010 *
b10001100101010001011010 2
0+
b0 1
b11000110010101000101101001001111010010100001000 3
b111010111111100001100 /
b10001110001100101010001011010 -
b1000010010111110010110 .
b110000111010111111100001100 $
b110000111010111111100001100 )
b1001011001000010010111110010110 #
b1001011001000010010111110010110 (
1"
b101011 '
#2280
0"
#2285
b10001110001100101010001011010 !
b10001110001100101010001011010 ,
1"
