f_divider/mantissa_divider.v
module mantissa_divider #(
    parameter BIT_WIDTH=23
) (
    input [31:0] in0,
    input [31:0] in1,
    output [BIT_WIDTH-1:0] out,
    output carry_down
);
//don't know in0_M>in1_M??
integer  i;

reg [BIT_WIDTH+1:0] A;
reg [BIT_WIDTH+1:0] Q;
reg [BIT_WIDTH+1:0] M;
reg [BIT_WIDTH+1:0] M_two_complement;
integer shitf_cnt;
wire [31:0] iter_max;
assign iter_max = BIT_WIDTH+1;
assign out=Q[BIT_WIDTH:1];
reg carry_down;
always @(*) begin
    //initial 
    carry_down=0;
    shitf_cnt=0;
    A=0;
    Q=0;
    A={2'b01,{in0[BIT_WIDTH-1:0]}};
    M={2'b01,{in1[BIT_WIDTH-1:0]}};
    //2의 보수화
    M_two_complement= ~M + {{(BIT_WIDTH+1){1'b0}},1'b1};
    i=0;
    while (i<iter_max) begin
    
         if(A>M) begin
            //#10;
            A=A+M_two_complement;
            Q[0]=1'b1;
            A=A<<1;
            Q=Q<<1;
            i=i+1;
        end else begin
            //#10;
            A=A<<1;
            Q=Q<<1;
            i=i+1;
        end
    end

    //last
    if(A>M) begin
           // #10;
            A=A+M_two_complement;
            Q[0]=1'b1;
    end

    carry_down=~Q[BIT_WIDTH+1];
    if(carry_down)begin
       Q=Q<<1; 
    end
end
//can't take     

function calIterBIt;
input bit_width;
integer i;
begin
    calIterBIt=0;
    for(i=bit_width;i>0;i++) begin
        i=i>>1;
        calIterBIt=calIterBIt+1;
    end
end
endfunction
endmodule

f_divider/f_divider_slow.v
`timescale 1ns/1ns
`include "mantissa_divider.v"
module f_divider_slow(
    input clk,
    input rstn,
    input [31:0] in0,
    input [31:0] in1,
    output reg [31:0] out
);
//in0/in1 
reg [31:0] res;
wire carry;
wire [FRACTION_BIT_WIDTH-1:0]out_fraction;
localparam FLOAT_32_BIAS = 8'h7f; //127 
localparam FRACTION_BIT_WIDTH = 23;

mantissa_divider#(
    .BIT_WIDTH(FRACTION_BIT_WIDTH)
) u_mantisaa_divider_0 (
    .in0(in0),
    .in1(in1),
    .out(out_fraction),
    .carry_down(carry)
);

always@(posedge clk or negedge rstn)begin
    if(!rstn) begin
        out <={32{1'b0}};
    end
    else begin
        out <= res;
    end
end 

always@(*)begin
    //cal sign bit
    res[31]=in0[31]^in1[31];

    //cal bias
    if(in0[30:23]<in1[30:23])begin
        res[30:23]=in1[30:23]-in0[30:23]+FLOAT_32_BIAS;
    end else begin
        res[30:23]=in0[30:23]-in1[30:23]+FLOAT_32_BIAS;
    end
    if(carry) res[30:23]=res[30:23]-1'b1;
    res[0+:FRACTION_BIT_WIDTH]=out_fraction;

end

endmodule

f_divider/f_divider_slow_tb.v
`timescale 1ns/1ns
`include "f_divider_slow.v"

module f_divider_slow_tb;

localparam BIT_WIDTH=32;
reg clk,rstn;
reg [BIT_WIDTH-1:0] in0;
reg [BIT_WIDTH-1:0] in1;
wire [BIT_WIDTH-1:0] out;

reg [22:0]r_in0,r_in1;

integer i;
integer f;

f_divider_slow u_f_divider_slow(
    .clk(clk),
    .rstn(rstn),
    .in0(in0),
    .in1(in1),
    .out(out)
);

always #5 clk = ~clk;

initial begin
    $dumpfile("f_divider_slow.vcd");
    $dumpvars(0);
end

initial begin
    f=$fopen("f_divider_slow_log.txt");
    $display("start time... [$0d]\n",$time);
    rstn = 0 ; clk = 0; in0=0; in1=0;
    $display("reset start...! [%0d]\n",$time);
    #100 rstn =0 ;
    #10 rstn =1;
    $display("reset end.. push random data...[$0d]\n",$time);

     for(i=0;i<128;i++)begin
        @(posedge clk);
        r_in0=$random;
        r_in1=$random;
        in0={1'b0,8'b01111111,r_in0};
        in1={1'b0,8'b00000001,r_in1};

        #50
        $fwrite(f,"%b\n",in0);
        $fwrite(f,"%b\n",in1);
        $fwrite(f,"%b\n",out);
    end
    #100 $fwrite(f,"quit!");
    $finish;

end

endmodule

f_divider/f_divider_slow.vcd
$date
	Mon Jan  2 21:02:41 2023
$end
$version
	Icarus Verilog
$end
$timescale
	1ns
$end
$scope module f_divider_slow_tb $end
$var wire 32 ! out [31:0] $end
$var reg 1 " clk $end
$var reg 32 # in0 [31:0] $end
$var reg 32 $ in1 [31:0] $end
$var reg 23 % r_in0 [22:0] $end
$var reg 23 & r_in1 [22:0] $end
$var reg 1 ' rstn $end
$var integer 32 ( f [31:0] $end
$var integer 32 ) i [31:0] $end
$scope module u_f_divider_slow $end
$var wire 1 " clk $end
$var wire 32 * in0 [31:0] $end
$var wire 32 + in1 [31:0] $end
$var wire 1 ' rstn $end
$var wire 23 , out_fraction [22:0] $end
$var wire 1 - carry $end
$var reg 32 . out [31:0] $end
$var reg 32 / res [31:0] $end
$scope module u_mantisaa_divider_0 $end
$var wire 32 0 in0 [31:0] $end
$var wire 32 1 in1 [31:0] $end
$var wire 32 2 iter_max [31:0] $end
$var wire 23 3 out [22:0] $end
$var reg 25 4 A [24:0] $end
$var reg 25 5 M [24:0] $end
$var reg 25 6 M_two_complement [24:0] $end
$var reg 25 7 Q [24:0] $end
$var reg 1 - carry_down $end
$var integer 32 8 i [31:0] $end
$var integer 32 9 shitf_cnt [31:0] $end
$scope function calIterBIt $end
$var reg 1 : bit_width $end
$var integer 32 ; i [31:0] $end
$upscope $end
$upscope $end
$upscope $end
$upscope $end
$enddefinitions $end
#0
$dumpvars
bx ;
x:
b0 9
b11000 8
b1111111111111111111111110 7
b1100000000000000000000000 6
b100000000000000000000000 5
b100000000000000000000000 4
b11111111111111111111111 3
b11000 2
b0 1
b0 0
b111111011111111111111111111111 /
b0 .
1-
b11111111111111111111111 ,
b0 +
b0 *
bx )
b10 (
0'
bx &
bx %
b0 $
b0 #
0"
b0 !
$end
#5
1"
#10
0"
#15
1"
#20
0"
#25
1"
#30
0"
#35
1"
#40
0"
#45
1"
#50
0"
#55
1"
#60
0"
#65
1"
#70
0"
#75
1"
#80
0"
#85
1"
#90
0"
#95
1"
#100
0"
#105
1"
#110
0"
b0 )
1'
#115
b111111011111111111111111111111 !
b111111011111111111111111111111 .
b10110000011111101111 ,
b10110000011111101111 3
b11000 8
b1011101101010000101111111 6
b100010010101111010000001 5
b1000101100000111111011110 7
b10000000111110100100010 4
0-
b1111110100010110000011111101111 /
b100010010101111010000001 $
b100010010101111010000001 +
b100010010101111010000001 1
b111111100101010011010100100100 #
b111111100101010011010100100100 *
b111111100101010011010100100100 0
b10010101111010000001 &
b101010011010100100100 %
1"
#120
0"
#125
b1111110100010110000011111101111 !
b1111110100010110000011111101111 .
1"
#130
0"
#135
1"
#140
0"
#145
1"
#150
0"
#155
1"
#160
0"
#165
b1111110000011010111111000101100 /
b11010111111000101100 ,
b11010111111000101100 3
1-
b11000 8
b1000011111010100110011101 6
b111100000101011001100011 5
b1000110101111110001011000 7
b101001010110110011111100 4
b111100000101011001100011 $
b111100000101011001100011 +
b111100000101011001100011 1
b111111100001001101011000001001 #
b111111100001001101011000001001 *
b111111100001001101011000001001 0
b11100000101011001100011 &
b1001101011000001001 %
1"
b1 )
#170
0"
#175
b1111110000011010111111000101100 !
b1111110000011010111111000101100 .
1"
#180
0"
#185
1"
#190
0"
#195
1"
#200
0"
#205
1"
#210
0"
#215
b10101000101101101110111 ,
b10101000101101101110111 3
b11000 8
b1001000000110011001110011 6
b110111111001100110001101 5
b1101010001011011011101110 7
b101101101000000001110101 4
1-
b1111110010101000101101101110111 /
b110111111001100110001101 $
b110111111001100110001101 +
b110111111001100110001101 1
b111111101110010111101100001101 #
b111111101110010111101100001101 *
b111111101110010111101100001101 0
b10111111001100110001101 &
b1110010111101100001101 %
1"
b10 )
#220
0"
#225
b1111110010101000101101101110111 !
b1111110010101000101101101110111 .
1"
#230
0"
#235
1"
#240
0"
#245
1"
#250
0"
#255
1"
#260
0"
#265
b1111101000101011010 ,
b1111101000101011010 3
b11000 8
b1010010001010110111101110 6
b101101110101001000010010 5
b1000011111010001010110101 7
b11001011001010101000110 4
0-
b1111110100001111101000101011010 /
b101101110101001000010010 $
b101101110101001000010010 +
b101101110101001000010010 1
b111111110000101000010001100101 #
b111111110000101000010001100101 *
b111111110000101000010001100101 0
b1101110101001000010010 &
b10000101000010001100101 %
1"
b11 )
#270
0"
#275
b1111110100001111101000101011010 !
b1111110100001111101000101011010 .
1"
#280
0"
#285
1"
#290
0"
#295
1"
#300
0"
#305
1"
#310
0"
#315
b1111110100100001010100010100100 /
b100001010100010100100 ,
b100001010100010100100 3
b11000 8
b1001010000011001011110011 6
b110101111100110100001101 5
b1001000010101000101001000 7
b110000000011011101011000 4
b110101111100110100001101 $
b110101111100110100001101 +
b110101111100110100001101 1
b111111111100111110001100000001 #
b111111111100111110001100000001 *
b111111111100111110001100000001 0
b10101111100110100001101 &
b11100111110001100000001 %
1"
b100 )
#320
0"
#325
b1111110100100001010100010100100 !
b1111110100100001010100010100100 .
1"
#330
0"
#335
1"
#340
0"
#345
1"
#350
0"
#355
1"
#360
0"
#365
b1111110100100111111110010000111 /
b100111111110010000111 ,
b100111111110010000111 3
b11000 8
b1011100100011001011000011 6
b100011011100110100111101 5
b1001001111111100100001110 7
b10100110111000110101010 4
b100011011100110100111101 $
b100011011100110100111101 +
b100011011100110100111101 1
b111111101000111111000101110110 #
b111111101000111111000101110110 *
b111111101000111111000101110110 0
b11011100110100111101 &
b1000111111000101110110 %
1"
b101 )
#370
0"
#375
b1111110100100111111110010000111 !
b1111110100100111111110010000111 .
1"
#380
0"
#385
1"
#390
0"
#395
1"
#400
0"
#405
1"
#410
0"
#415
b1111110100111000011110010000000 /
b111000011110010000000 ,
b111000011110010000000 3
b11000 8
b1010100100000100001110100 6
b101011011111011110001100 5
b1001110000111100100000000 7
b10111101101010000000000 4
b101011011111011110001100 $
b101011011111011110001100 +
b101011011111011110001100 1
b111111110101000101011111101101 #
b111111110101000101011111101101 *
b111111110101000101011111101101 0
b1011011111011110001100 &
b10101000101011111101101 %
1"
b110 )
#420
0"
#425
b1111110100111000011110010000000 !
b1111110100111000011110010000000 .
1"
#430
0"
#435
1"
#440
0"
#445
1"
#450
0"
#455
1"
#460
0"
#465
b1111110101100010111011000110011 /
b1100010111011000110011 ,
b1100010111011000110011 3
b11000 8
b1010010001101101100111010 6
b101101110010010011000110 5
b1011000101110110001100110 7
b10101001101000100011100 4
b101101110010010011000110 $
b101101110010010011000110 +
b101101110010010011000110 1
b111111111111011110100111111001 #
b111111111111011110100111111001 *
b111111111111011110100111111001 0
b1101110010010011000110 &
b11111011110100111111001 %
1"
b111 )
#470
0"
#475
b1111110101100010111011000110011 !
b1111110101100010111011000110011 .
1"
#480
0"
#485
1"
#490
0"
#495
1"
#500
0"
#505
1"
#510
0"
#515
b1111110110101100101001110011101 /
b10101100101001110011101 ,
b10101100101001110011101 3
b11000 8
b1011011000010110101010110 6
b100100111101001010101010 5
b1101011001010011100111011 7
b10010011000110011010010 4
b100100111101001010101010 $
b100100111101001010101010 +
b100100111101001010101010 1
b111111111101111000010011000101 #
b111111111101111000010011000101 *
b111111111101111000010011000101 0
b100111101001010101010 &
b11101111000010011000101 %
1"
b1000 )
#520
0"
#525
b1111110110101100101001110011101 !
b1111110110101100101001110011101 .
1"
#530
0"
#535
1"
#540
0"
#545
1"
#550
0"
#555
1"
#560
0"
#565
b1111110010101100000111011011010 /
b10101100000111011011010 ,
b10101100000111011011010 3
1-
b11000 8
b1001011011000110110001001 6
b110100100111001001110111 5
b1101011000001110110110100 7
b11100000010010101010 4
b110100100111001001110111 $
b110100100111001001110111 +
b110100100111001001110111 1
b111111101011111111011111100101 #
b111111101011111111011111100101 *
b111111101011111111011111100101 0
b10100100111001001110111 &
b1011111111011111100101 %
1"
b1001 )
#570
0"
#575
b1111110010101100000111011011010 !
b1111110010101100000111011011010 .
1"
#580
0"
#585
1"
#590
0"
#595
1"
#600
0"
#605
1"
#610
0"
#615
b10000010100101000010101 ,
b10000010100101000010101 3
b11000 8
b1000100110010010001110001 6
b111011001101101110001111 5
b1100000101001010000101010 7
b10010111010011101000101 4
1-
b1111110010000010100101000010101 /
b111011001101101110001111 $
b111011001101101110001111 +
b111011001101101110001111 1
b111111101100101101011000010010 #
b111111101100101101011000010010 *
b111111101100101101011000010010 0
b11011001101101110001111 &
b1100101101011000010010 %
1"
b1010 )
#620
0"
#625
b1111110010000010100101000010101 !
b1111110010000010100101000010101 .
1"
#630
0"
#635
1"
#640
0"
#645
1"
#650
0"
#655
1"
#660
0"
#665
b1101110010010110000101 ,
b1101110010010110000101 3
b11000 8
b1000010010110100100110010 6
b111101101001011011001110 5
b1011011100100101100001010 7
b110101011110000011111010 4
1-
b1111110001101110010010110000101 /
b111101101001011011001110 $
b111101101001011011001110 +
b111101101001011011001110 1
b111111101100000110100111110010 #
b111111101100000110100111110010 *
b111111101100000110100111110010 0
b11101101001011011001110 &
b1100000110100111110010 %
1"
b1011 )
#670
0"
#675
b1111110001101110010010110000101 !
b1111110001101110010010110000101 .
1"
#680
0"
#685
1"
#690
0"
#695
1"
#700
0"
#705
1"
#710
0"
#715
b1000101001010000100000 ,
b1000101001010000100000 3
b11000 8
b1001101011011000100111011 6
b110010100100111011000101 5
b1010001010010100001000000 7
b100000100100001101100000 4
1-
b1111110001000101001010000100000 /
b110010100100111011000101 $
b110010100100111011000101 +
b110010100100111011000101 1
b111111100000000111101011101000 #
b111111100000000111101011101000 *
b111111100000000111101011101000 0
b10010100100111011000101 &
b111101011101000 %
1"
b1100 )
#720
0"
#725
b1111110001000101001010000100000 !
b1111110001000101001010000100000 .
1"
#730
0"
#735
1"
#740
0"
#745
1"
#750
0"
#755
1"
#760
0"
#765
b10000101011111010001001 ,
b10000101011111010001001 3
b11000 8
b1011100011101011101000011 6
b100011100010100010111101 5
b1100001010111110100010011 7
b10111011011000011111001 4
0-
b1111110110000101011111010001001 /
b100011100010100010111101 $
b100011100010100010111101 +
b100011100010100010111101 1
b111111110110000100100101011100 #
b111111110110000100100101011100 *
b111111110110000100100101011100 0
b11100010100010111101 &
b10110000100100101011100 %
1"
b1101 )
#770
0"
#775
b1111110110000101011111010001001 !
b1111110110000101011111010001001 .
1"
#780
0"
#785
1"
#790
0"
#795
1"
#800
0"
#805
1"
#810
0"
#815
b1111110100000110011011001000111 /
b110011011001000111 ,
b110011011001000111 3
b11000 8
b1010110001101100110011011 6
b101001110010011001100101 5
b1000001100110110010001111 7
b100001111000110010101 4
b101001110010011001100101 $
b101001110010011001100101 +
b101001110010011001100101 1
b111111101010110101100000101101 #
b111111101010110101100000101101 *
b111111101010110101100000101101 0
b1001110010011001100101 &
b1010110101100000101101 %
1"
b1110 )
#820
0"
#825
b1111110100000110011011001000111 !
b1111110100000110011011001000111 .
1"
#830
0"
#835
1"
#840
0"
#845
1"
#850
0"
#855
1"
#860
0"
#865
b1111110011110111010010100000110 /
b11110111010010100000110 ,
b11110111010010100000110 3
1-
b11000 8
b1000011000111100011110110 6
b111100111000011100001010 5
b1111101110100101000001100 7
b11100110110001111000100 4
b111100111000011100001010 $
b111100111000011100001010 +
b111100111000011100001010 1
b111111111011110110001001100011 #
b111111111011110110001001100011 *
b111111111011110110001001100011 0
b11100111000011100001010 &
b11011110110001001100011 %
1"
b1111 )
#870
0"
#875
b1111110011110111010010100000110 !
b1111110011110111010010100000110 .
1"
#880
0"
#885
1"
#890
0"
#895
1"
#900
0"
#905
1"
#910
0"
#915
b10100011111111100111110 ,
b10100011111111100111110 3
b11000 8
b1000110111101111011100000 6
b111001000010000100100000 5
b1101000111111111001111100 7
b101000010001101001000000 4
1-
b1111110010100011111111100111110 /
b111001000010000100100000 $
b111001000010000100100000 +
b111001000010000100100000 1
b111111101110110010001010000000 #
b111111101110110010001010000000 *
b111111101110110010001010000000 0
b11001000010000100100000 &
b1110110010001010000000 %
1"
b10000 )
#920
0"
#925
b1111110010100011111111100111110 !
b1111110010100011111111100111110 .
1"
#930
0"
#935
1"
#940
0"
#945
1"
#950
0"
#955
1"
#960
0"
#965
b110110010101110101110 ,
b110110010101110101110 3
b11000 8
b1001100110011001101100011 6
b110011001100110010011101 5
b1001101100101011101011100 7
b101111110001110010010100 4
0-
b1111110100110110010101110101110 /
b110011001100110010011101 $
b110011001100110010011101 +
b110011001100110010011101 1
b111111111110000100010110101010 #
b111111111110000100010110101010 *
b111111111110000100010110101010 0
b10011001100110010011101 &
b11110000100010110101010 %
1"
b10001 )
#970
0"
#975
b1111110100110110010101110101110 !
b1111110100110110010101110101110 .
1"
#980
0"
#985
1"
#990
0"
#995
1"
#1000
0"
#1005
1"
#1010
0"
#1015
b1111110100110111011100001010011 /
b110111011100001010011 ,
b110111011100001010011 3
b11000 8
b1011111000100011111101101 6
b100000111011100000010011 5
b1001101110111000010100111 7
b11101011001101110011011 4
b100000111011100000010011 $
b100000111011100000010011 +
b100000111011100000010011 1
b111111101000000011111010010110 #
b111111101000000011111010010110 *
b111111101000000011111010010110 0
b111011100000010011 &
b1000000011111010010110 %
1"
b10010 )
#1020
0"
#1025
b1111110100110111011100001010011 !
b1111110100110111011100001010011 .
1"
#1030
0"
#1035
1"
#1040
0"
#1045
1"
#1050
0"
#1055
1"
#1060
0"
#1065
b1111110100011111000101101000100 /
b11111000101101000100 ,
b11111000101101000100 3
b11000 8
b1010110000010100110101101 6
b101001111101011001010011 5
b1000111110001011010001000 7
b10111100000000111101000 4
b101001111101011001010011 $
b101001111101011001010011 +
b101001111101011001010011 1
b111111101111000011100000001101 #
b111111101111000011100000001101 *
b111111101111000011100000001101 0
b1001111101011001010011 &
b1111000011100000001101 %
1"
b10011 )
#1070
0"
#1075
b1111110100011111000101101000100 !
b1111110100011111000101101000100 .
1"
#1080
0"
#1085
1"
#1090
0"
#1095
1"
#1100
0"
#1105
1"
#1110
0"
#1115
b1111110011101100100101001011001 /
b11101100100101001011001 ,
b11101100100101001011001 3
1-
b11000 8
b1010110011101010100101011 6
b101001100010101011010101 5
b1111011001001010010110010 7
b1010111000100111110011 4
b101001100010101011010101 $
b101001100010101011010101 +
b101001100010101011010101 1
b111111100111111101110101101011 #
b111111100111111101110101101011 *
b111111100111111101110101101011 0
b1001100010101011010101 &
b111111101110101101011 %
1"
b10100 )
#1120
0"
#1125
b1111110011101100100101001011001 !
b1111110011101100100101001011001 .
1"
#1130
0"
#1135
1"
#1140
0"
#1145
1"
#1150
0"
#1155
1"
#1160
0"
#1165
b1101001100011001000110 ,
b1101001100011001000110 3
b11000 8
b1001010011100000101010010 6
b110101100011111010101110 5
b1011010011000110010001100 7
b100110000100100001101100 4
1-
b1111110001101001100011001000110 /
b110101100011111010101110 $
b110101100011111010101110 +
b110101100011111010101110 1
b111111100101110100101000000010 #
b111111100101110100101000000010 *
b111111100101110100101000000010 0
b10101100011111010101110 &
b101110100101000000010 %
1"
b10101 )
#1170
0"
#1175
b1111110001101001100011001000110 !
b1111110001101001100011001000110 .
1"
#1180
0"
#1185
1"
#1190
0"
#1195
1"
#1200
0"
#1205
1"
#1210
0"
#1215
b1001011110011000110110 ,
b1001011110011000110110 3
b11000 8
b1001110101000110100110001 6
b110001010111001011001111 5
b1010010111100110001101100 7
b100100011001110010101100 4
0-
b1111110101001011110011000110110 /
b110001010111001011001111 $
b110001010111001011001111 +
b110001010111001011001111 1
b111111111111111110100100011101 #
b111111111111111110100100011101 *
b111111111111111110100100011101 0
b10001010111001011001111 &
b11111111110100100011101 %
1"
b10110 )
#1220
0"
#1225
b1111110101001011110011000110110 !
b1111110101001011110011000110110 .
1"
#1230
0"
#1235
1"
#1240
0"
#1245
1"
#1250
0"
#1255
1"
#1260
0"
#1265
b1111110011101100111101100001110 /
b11101100111101100001110 ,
b11101100111101100001110 3
1-
b11000 8
b1011101101001101011110110 6
b100010010110010100001010 5
b1111011001111011000011100 7
b10101001010101101110100 4
b100010010110010100001010 $
b100010010110010100001010 +
b100010010110010100001010 1
b111111100001000100100100100011 #
b111111100001000100100100100011 *
b111111100001000100100100100011 0
b10010110010100001010 &
b1000100100100100011 %
1"
b10111 )
#1270
0"
#1275
b1111110011101100111101100001110 !
b1111110011101100111101100001110 .
1"
#1280
0"
#1285
1"
#1290
0"
#1295
1"
#1300
0"
#1305
1"
#1310
0"
#1315
b1011110111011011001110 ,
b1011110111011011001110 3
b11000 8
b1010011101011001111000100 6
b101100010100110000111100 5
b1010111101110110110011100 7
b10110011111111101110000 4
0-
b1111110101011110111011011001110 /
b101100010100110000111100 $
b101100010100110000111100 +
b101100010100110000111100 1
b111111111100110000101011001010 #
b111111111100110000101011001010 *
b111111111100110000101011001010 0
b1100010100110000111100 &
b11100110000101011001010 %
1"
b11000 )
#1320
0"
#1325
b1111110101011110111011011001110 !
b1111110101011110111011011001110 .
1"
#1330
0"
#1335
1"
#1340
0"
#1345
1"
#1350
0"
#1355
1"
#1360
0"
#1365
b1111110101010101101011010100001 /
b1010101101011010100001 ,
b1010101101011010100001 3
b11000 8
b1010100011001111001110110 6
b101011100110000110001010 5
b1010101011010110101000010 7
b10011101001100001101100 4
b101011100110000110001010 $
b101011100110000110001010 +
b101011100110000110001010 1
b111111111010001011110111110010 #
b111111111010001011110111110010 *
b111111111010001011110111110010 0
b1011100110000110001010 &
b11010001011110111110010 %
1"
b11001 )
#1370
0"
#1375
b1111110101010101101011010100001 !
b1111110101010101101011010100001 .
1"
#1380
0"
#1385
1"
#1390
0"
#1395
1"
#1400
0"
#1405
1"
#1410
0"
#1415
b1111110011101111100110110101111 /
b11101111100110110101111 ,
b11101111100110110101111 3
1-
b11000 8
b1001101001100101100101000 6
b110010110011010011011000 5
b1111011111001101101011110 7
b10111011110100001011000 4
b110010110011010011011000 $
b110010110011010011011000 +
b110010110011010011011000 1
b111111110001001011001101000001 #
b111111110001001011001101000001 *
b111111110001001011001101000001 0
b10010110011010011011000 &
b10001001011001101000001 %
1"
b11010 )
#1420
0"
#1425
b1111110011101111100110110101111 !
b1111110011101111100110110101111 .
1"
#1430
0"
#1435
1"
#1440
0"
#1445
1"
#1450
0"
#1455
1"
#1460
0"
#1465
b101010011010110101011 ,
b101010011010110101011 3
b11000 8
b1011101011110110101110111 6
b100010100001001010001001 5
b1001010100110101101010110 7
b11001001000001011111010 4
0-
b1111110100101010011010110101011 /
b100010100001001010001001 $
b100010100001001010001001 +
b100010100001001010001001 1
b111111101000001111001101111000 #
b111111101000001111001101111000 *
b111111101000001111001101111000 0
b10100001001010001001 &
b1000001111001101111000 %
1"
b11011 )
#1470
0"
#1475
b1111110100101010011010110101011 !
b1111110100101010011010110101011 .
1"
#1480
0"
#1485
1"
#1490
0"
#1495
1"
#1500
0"
#1505
1"
#1510
0"
#1515
b1111110110000010110111001111100 /
b10000010110111001111100 ,
b10000010110111001111100 3
b11000 8
b1011111011001101001001010 6
b100000100110010110110110 5
b1100000101101110011111001 7
b10101101010100111111010 4
b100000100110010110110110 $
b100000100110010110110110 +
b100000100110010110110110 1
b111111110001010000110111101011 #
b111111110001010000110111101011 *
b111111110001010000110111101011 0
b100110010110110110 &
b10001010000110111101011 %
1"
b11100 )
#1520
0"
#1525
b1111110110000010110111001111100 !
b1111110110000010110111001111100 .
1"
#1530
0"
#1535
1"
#1540
0"
#1545
1"
#1550
0"
#1555
1"
#1560
0"
#1565
b1111110101011110010001100010110 /
b1011110010001100010110 ,
b1011110010001100010110 3
b11000 8
b1011010101110110001010010 6
b100101010001001110101110 5
b1010111100100011000101101 7
b100001011111011001101010 4
b100101010001001110101110 $
b100101010001001110101110 +
b100101010001001110101110 1
b111111110010111111100111000110 #
b111111110010111111100111000110 *
b111111110010111111100111000110 0
b101010001001110101110 &
b10010111111100111000110 %
1"
b11101 )
#1570
0"
#1575
b1111110101011110010001100010110 !
b1111110101011110010001100010110 .
1"
#1580
0"
#1585
1"
#1590
0"
#1595
1"
#1600
0"
#1605
1"
#1610
0"
#1615
b1111110110110011111111001000111 /
b10110011111111001000111 ,
b10110011111111001000111 3
b11000 8
b1011100000010001011010110 6
b100011111101110100101010 5
b1101100111111110010001110 7
b111111111101010110100 4
b100011111101110100101010 $
b100011111101110100101010 +
b100011111101110100101010 1
b111111111101010000001010111100 #
b111111111101010000001010111100 *
b111111111101010000001010111100 0
b11111101110100101010 &
b11101010000001010111100 %
1"
b11110 )
#1620
0"
#1625
b1111110110110011111111001000111 !
b1111110110110011111111001000111 .
1"
#1630
0"
#1635
1"
#1640
0"
#1645
1"
#1650
0"
#1655
1"
#1660
0"
#1665
b1111110101101011101110110100010 /
b1101011101110110100010 ,
b1101011101110110100010 3
b11000 8
b1011010000100000110001111 6
b100101111011111001110001 5
b1011010111011101101000100 7
b10110011101111011111100 4
b100101111011111001110001 $
b100101111011111001110001 +
b100101111011111001110001 1
b111111110101111001101000001011 #
b111111110101111001101000001011 *
b111111110101111001101000001011 0
b101111011111001110001 &
b10101111001101000001011 %
1"
b11111 )
#1670
0"
#1675
b1111110101101011101110110100010 !
b1111110101101011101110110100010 .
1"
#1680
0"
#1685
1"
#1690
0"
#1695
1"
#1700
0"
#1705
1"
#1710
0"
#1715
b1111110011111111110101100011000 /
b11111111110101100011000 ,
b11111111110101100011000 3
1-
b11000 8
b1000011011010101010110001 6
b111100100101010101001111 5
b1111111111101011000110000 7
b10001110111101110011000 4
b111100100101010101001111 $
b111100100101010101001111 +
b111100100101010101001111 1
b111111111100100100000110000101 #
b111111111100100100000110000101 *
b111111111100100100000110000101 0
b11100100101010101001111 &
b11100100100000110000101 %
1"
b100000 )
#1720
0"
#1725
b1111110011111111110101100011000 !
b1111110011111111110101100011000 .
1"
#1730
0"
#1735
1"
#1740
0"
#1745
1"
#1750
0"
#1755
1"
#1760
0"
#1765
b10000101110111100000011 ,
b10000101110111100000011 3
b11000 8
b1011110011100110011000110 6
b100001100011001100111010 5
b1100001011101111000000110 7
b10011001000000010100100 4
0-
b1111110110000101110111100000011 /
b100001100011001100111010 $
b100001100011001100111010 +
b100001100011001100111010 1
b111111110011000110000000111011 #
b111111110011000110000000111011 *
b111111110011000110000000111011 0
b1100011001100111010 &
b10011000110000000111011 %
1"
b100001 )
#1770
0"
#1775
b1111110110000101110111100000011 !
b1111110110000101110111100000011 .
1"
#1780
0"
#1785
1"
#1790
0"
#1795
1"
#1800
0"
#1805
1"
#1810
0"
#1815
b1111110011101010101010100100100 /
b11101010101010100100100 ,
b11101010101010100100100 3
1-
b11000 8
b1010101011011010011101011 6
b101010100100101100010101 5
b1111010101010101001001000 7
b1100111100000001100 4
b101010100100101100010101 $
b101010100100101100010101 +
b101010100100101100010101 1
b111111101000110011001001111110 #
b111111101000110011001001111110 *
b111111101000110011001001111110 0
b1010100100101100010101 &
b1000110011001001111110 %
1"
b100010 )
#1820
0"
#1825
b1111110011101010101010100100100 !
b1111110011101010101010100100100 .
1"
#1830
0"
#1835
1"
#1840
0"
#1845
1"
#1850
0"
#1855
1"
#1860
0"
#1865
b1100100011011001101110 ,
b1100100011011001101110 3
b11000 8
b1011000111011010000100111 6
b100111000100101111011001 5
b1011001000110110011011101 7
b10011101111100110101011 4
0-
b1111110101100100011011001101110 /
b100111000100101111011001 $
b100111000100101111011001 +
b100111000100101111011001 1
b111111110110011001101111110001 #
b111111110110011001101111110001 *
b111111110110011001101111110001 0
b111000100101111011001 &
b10110011001101111110001 %
1"
b100011 )
#1870
0"
#1875
b1111110101100100011011001101110 !
b1111110101100100011011001101110 .
1"
#1880
0"
#1885
1"
#1890
0"
#1895
1"
#1900
0"
#1905
1"
#1910
0"
#1915
b1111110011001010101011010100100 /
b11001010101011010100100 ,
b11001010101011010100100 3
1-
b11000 8
b1010010100000010010110100 6
b101101011111101101001100 5
b1110010101010110101001000 7
b110111101101010000 4
b101101011111101101001100 $
b101101011111101101001100 +
b101101011111101101001100 1
b111111101000110000011101100010 #
b111111101000110000011101100010 *
b111111101000110000011101100010 0
b1101011111101101001100 &
b1000110000011101100010 %
1"
b100100 )
#1920
0"
#1925
b1111110011001010101011010100100 !
b1111110011001010101011010100100 .
1"
#1930
0"
#1935
1"
#1940
0"
#1945
1"
#1950
0"
#1955
1"
#1960
0"
#1965
b10111100111111000110110 ,
b10111100111111000110110 3
b11000 8
b1010001100101111001110001 6
b101110011010000110001111 5
b1101111001111110001101100 7
b10100011000100111010110 4
1-
b1111110010111100111111000110110 /
b101110011010000110001111 $
b101110011010000110001111 +
b101110011010000110001111 1
b111111101000010101010110011111 #
b111111101000010101010110011111 *
b111111101000010101010110011111 0
b1110011010000110001111 &
b1000010101010110011111 %
1"
b100101 )
#1970
0"
#1975
b1111110010111100111111000110110 !
b1111110010111100111111000110110 .
1"
#1980
0"
#1985
1"
#1990
0"
#1995
1"
#2000
0"
#2005
1"
#2010
0"
#2015
b101000001111101000000 ,
b101000001111101000000 3
b11000 8
b1001100101001111101001001 6
b110011010110000010110111 5
b1001010000011111010000000 7
b10010110101001010000000 4
0-
b1111110100101000001111101000000 /
b110011010110000010110111 $
b110011010110000010110111 +
b110011010110000010110111 1
b111111111011011010100111111000 #
b111111111011011010100111111000 *
b111111111011011010100111111000 0
b10011010110000010110111 &
b11011011010100111111000 %
1"
b100110 )
#2020
0"
#2025
b1111110100101000001111101000000 !
b1111110100101000001111101000000 .
1"
#2030
0"
#2035
1"
#2040
0"
#2045
1"
#2050
0"
#2055
1"
#2060
0"
#2065
b1111110010001100011011001100011 /
b10001100011011001100011 ,
b10001100011011001100011 3
1-
b11000 8
b1000000100110101110100100 6
b111111011001010001011100 5
b1100011000110110011000110 7
b11111000011100001101100 4
b111111011001010001011100 $
b111111011001010001011100 +
b111111011001010001011100 1
b111111110001000101011010011111 #
b111111110001000101011010011111 *
b111111110001000101011010011111 0
b11111011001010001011100 &
b10001000101011010011111 %
1"
b100111 )
#2070
0"
#2075
b1111110010001100011011001100011 !
b1111110010001100011011001100011 .
1"
#2080
0"
