f_divider/mantissa_divider.v
module mantissa_divider #(
    parameter BIT_WIDTH=23
) (
    input [31:0] in0,
    input [31:0] in1,
    output [BIT_WIDTH-1:0] out
);
//don't know in0_M>in1_M??
integer  i;
reg [2*BIT_WIDTH+1:0] A_Q;
reg [BIT_WIDTH+1:0] M;
reg [BIT_WIDTH+1:0] M_two_complement;
integer shitf_cnt;
wire [31:0] iter_max;
assign iter_max = BIT_WIDTH;
always @(*) begin
    //initial 
    shitf_cnt=0;
    A_Q=0;
    A_Q[2*BIT_WIDTH+1 -:BIT_WIDTH+2]={2'b01,{in0[BIT_WIDTH-1:0]}};
    M={2'b01,{in1[BIT_WIDTH-1:0]}};
    //2의 보수화
    M_two_complement= ~M + {{(BIT_WIDTH+1){1'b0}},1'b1};
    
    #10;
    for(i=0; i<iter_max; i=i+1)begin
        #10;
        shitf_cnt=shitf_cnt+1;
        if(A_Q[2*BIT_WIDTH+1 -:BIT_WIDTH+2]>M) begin
            A_Q[2*BIT_WIDTH+1 -:BIT_WIDTH+2]=A_Q[2*BIT_WIDTH+1 -:BIT_WIDTH+2]+M_two_complement;
            A_Q[0]=1'b1;
        end else begin
            A_Q[0]=1'b0;
        end
        #10;
        A_Q=A_Q<<1;
        // A_Q=A_Q<<1;

        // A_Q[2*BIT_WIDTH+1 -:BIT_WIDTH+1]=A_Q[2*BIT_WIDTH+1 -:BIT_WIDTH+1]+M_two_complement;
        // case (A_Q[2*BIT_WIDTH+1])
        //     1'b0:begin
        //         //q[LSB] = 1
        //         A_Q[0]=1'b1;
        //     end
        //     1'b1: begin
        //         //restore
        //         A_Q[2*BIT_WIDTH+1 -:BIT_WIDTH+1]=A_Q[2*BIT_WIDTH+1 -:BIT_WIDTH+1]+M;
        //         A_Q[0]=1'b0;
        //     end 
        // endcase
     
    end
    //shift 없는 연산 한번더
    if(A_Q[2*BIT_WIDTH+1 -:BIT_WIDTH+2]>M) begin
        A_Q[2*BIT_WIDTH+1 -:BIT_WIDTH+2]=A_Q[2*BIT_WIDTH+1 -:BIT_WIDTH+2]+M_two_complement;
        A_Q[0]=1'b1;
    end else begin
        A_Q[0]=1'b0;
    end
end
//can't take     

function calIterBIt;
input bit_width;
integer i;
begin
    calIterBIt=0;
    for(i=bit_width;i>0;i++) begin
        i=i>>1;
        calIterBIt=calIterBIt+1;
    end
end
endfunction
endmodule

f_divider/mantissa_divider_tb.v

`timescale 1ns/1ns
`include "mantissa_divider.v"
module mantissa_divider_tb;
    localparam  MY_BIT_WIDTH = 5;
    reg [31:0] in0,in1;
    wire [MY_BIT_WIDTH-1:0] out;
    
    
mantissa_divider #(
    .BIT_WIDTH(MY_BIT_WIDTH)
) u_mantisaa_divider(
    .in0(in0),
    .in1(in1),
    .out(out)
);

initial begin
    $dumpfile("mantisaa_divider.vcd");
    $dumpvars(0);
end

initial begin
    in0=5'b01100; in1=5'b00100;
    #1000 $finish;
end

endmodule

f_divider/mantisaa_divider.vcd
$date
	Wed Dec 21 20:46:52 2022
$end
$version
	Icarus Verilog
$end
$timescale
	1ns
$end
$scope module mantissa_divider_tb $end
$var wire 5 ! out [4:0] $end
$var reg 32 " in0 [31:0] $end
$var reg 32 # in1 [31:0] $end
$scope module u_mantisaa_divider $end
$var wire 32 $ in0 [31:0] $end
$var wire 32 % in1 [31:0] $end
$var wire 32 & iter_max [31:0] $end
$var wire 5 ' out [4:0] $end
$var reg 12 ( A_Q [11:0] $end
$var reg 7 ) M [6:0] $end
$var reg 7 * M_two_complement [6:0] $end
$var integer 32 + i [31:0] $end
$var integer 32 , shitf_cnt [31:0] $end
$scope function calIterBIt $end
$var reg 1 - bit_width $end
$var integer 32 . i [31:0] $end
$upscope $end
$upscope $end
$upscope $end
$enddefinitions $end
#0
$dumpvars
bx .
x-
b0 ,
bx +
b1011100 *
b100100 )
b10110000000 (
bz '
b101 &
b100 %
b1100 $
b100 #
b1100 "
bz !
$end
#10
b0 +
#20
b100000001 (
b1 ,
#30
b1 +
b1000000010 (
#40
b10 ,
#50
b10 +
b10000000100 (
#60
b11 ,
#70
b11 +
b100000001000 (
#80
b1110001001 (
b100 ,
#90
b100 +
b11100010010 (
#100
b1010010011 (
b101 ,
#110
b101 +
b10100111 (
